<?xml version="1.0" encoding="utf-8"?>
<BindInfo>
	<BindNode BINDTYPE="op" DISPLAY="bind_op icmp" ID="" IMPL="auto" LATENCY="0" OPTYPE="icmp" PRAGMA="" RTLNAME="icmp_ln24_fu_227_p2" SOURCE="d2.cpp:24" VARIABLE="icmp_ln24" MODULE="fiat_25519_carry_mul_Pipeline_ARRAY_1_READ" LOOP="ARRAY_1_READ" BUNDLEDNAME="" DSP="0" BRAM="0" URAM="0"/>
	<BindNode BINDTYPE="op" DISPLAY="bind_op add" ID="" IMPL="fabric" LATENCY="0" OPTYPE="add" PRAGMA="" RTLNAME="add_ln24_fu_233_p2" SOURCE="d2.cpp:24" VARIABLE="add_ln24" MODULE="fiat_25519_carry_mul_Pipeline_ARRAY_1_READ" LOOP="ARRAY_1_READ" BUNDLEDNAME="" DSP="0" BRAM="0" URAM="0"/>
	<BindNode BINDTYPE="op" DISPLAY="bind_op icmp" ID="" IMPL="auto" LATENCY="0" OPTYPE="icmp" PRAGMA="" RTLNAME="icmp_ln31_fu_227_p2" SOURCE="d2.cpp:31" VARIABLE="icmp_ln31" MODULE="fiat_25519_carry_mul_Pipeline_ARRAY_2_READ" LOOP="ARRAY_2_READ" BUNDLEDNAME="" DSP="0" BRAM="0" URAM="0"/>
	<BindNode BINDTYPE="op" DISPLAY="bind_op add" ID="" IMPL="fabric" LATENCY="0" OPTYPE="add" PRAGMA="" RTLNAME="add_ln31_fu_233_p2" SOURCE="d2.cpp:31" VARIABLE="add_ln31" MODULE="fiat_25519_carry_mul_Pipeline_ARRAY_2_READ" LOOP="ARRAY_2_READ" BUNDLEDNAME="" DSP="0" BRAM="0" URAM="0"/>
	<BindNode BINDTYPE="op" DISPLAY="bind_op icmp" ID="" IMPL="auto" LATENCY="0" OPTYPE="icmp" PRAGMA="" RTLNAME="icmp_ln36_fu_562_p2" SOURCE="d2.cpp:36" VARIABLE="icmp_ln36" MODULE="fiat_25519_carry_mul_Pipeline_VITIS_LOOP_36_1" LOOP="VITIS_LOOP_36_1" BUNDLEDNAME="" DSP="0" BRAM="0" URAM="0"/>
	<BindNode BINDTYPE="op" DISPLAY="bind_op mux" ID="" IMPL="auto" LATENCY="0" OPTYPE="mux" PRAGMA="" RTLNAME="mux_8_3_32_1_1_U66" SOURCE="d2.cpp:49" VARIABLE="tmp" MODULE="fiat_25519_carry_mul_Pipeline_VITIS_LOOP_36_1" LOOP="VITIS_LOOP_36_1" BUNDLEDNAME="" DSP="0" BRAM="0" URAM="0"/>
	<BindNode BINDTYPE="op" DISPLAY="bind_op xor" ID="" IMPL="auto" LATENCY="0" OPTYPE="xor" PRAGMA="" RTLNAME="cmp32_1111_fu_602_p2" SOURCE="" VARIABLE="cmp32_1111" MODULE="fiat_25519_carry_mul_Pipeline_VITIS_LOOP_36_1" LOOP="VITIS_LOOP_36_1" BUNDLEDNAME="" DSP="0" BRAM="0" URAM="0"/>
	<BindNode BINDTYPE="op" DISPLAY="bind_op mux" ID="" IMPL="auto" LATENCY="0" OPTYPE="mux" PRAGMA="" RTLNAME="mux_8_3_32_1_1_U67" SOURCE="d2.cpp:49" VARIABLE="tmp_1" MODULE="fiat_25519_carry_mul_Pipeline_VITIS_LOOP_36_1" LOOP="VITIS_LOOP_36_1" BUNDLEDNAME="" DSP="0" BRAM="0" URAM="0"/>
	<BindNode BINDTYPE="op" DISPLAY="bind_op mux" ID="" IMPL="auto" LATENCY="0" OPTYPE="mux" PRAGMA="" RTLNAME="mux_8_3_32_1_1_U68" SOURCE="d2.cpp:49" VARIABLE="tmp_2" MODULE="fiat_25519_carry_mul_Pipeline_VITIS_LOOP_36_1" LOOP="VITIS_LOOP_36_1" BUNDLEDNAME="" DSP="0" BRAM="0" URAM="0"/>
	<BindNode BINDTYPE="op" DISPLAY="bind_op add" ID="" IMPL="fabric" LATENCY="0" OPTYPE="add" PRAGMA="" RTLNAME="add_ln48_fu_652_p2" SOURCE="d2.cpp:48" VARIABLE="add_ln48" MODULE="fiat_25519_carry_mul_Pipeline_VITIS_LOOP_36_1" LOOP="VITIS_LOOP_36_1" BUNDLEDNAME="" DSP="0" BRAM="0" URAM="0"/>
	<BindNode BINDTYPE="op" DISPLAY="bind_op icmp" ID="" IMPL="auto" LATENCY="0" OPTYPE="icmp" PRAGMA="" RTLNAME="icmp_ln48_fu_658_p2" SOURCE="d2.cpp:48" VARIABLE="icmp_ln48" MODULE="fiat_25519_carry_mul_Pipeline_VITIS_LOOP_36_1" LOOP="VITIS_LOOP_36_1" BUNDLEDNAME="" DSP="0" BRAM="0" URAM="0"/>
	<BindNode BINDTYPE="op" DISPLAY="bind_op and" ID="" IMPL="auto" LATENCY="0" OPTYPE="and" PRAGMA="" RTLNAME="and_ln48_fu_664_p2" SOURCE="d2.cpp:48" VARIABLE="and_ln48" MODULE="fiat_25519_carry_mul_Pipeline_VITIS_LOOP_36_1" LOOP="VITIS_LOOP_36_1" BUNDLEDNAME="" DSP="0" BRAM="0" URAM="0"/>
	<BindNode BINDTYPE="op" DISPLAY="bind_op select" ID="" IMPL="auto_sel" LATENCY="0" OPTYPE="select" PRAGMA="" RTLNAME="mul_ln49_fu_429_p10" SOURCE="d2.cpp:49" VARIABLE="select_ln49" MODULE="fiat_25519_carry_mul_Pipeline_VITIS_LOOP_36_1" LOOP="VITIS_LOOP_36_1" BUNDLEDNAME="" DSP="0" BRAM="0" URAM="0"/>
	<BindNode BINDTYPE="op" DISPLAY="bind_op mul" ID="" IMPL="auto" LATENCY="0" OPTYPE="mul" PRAGMA="" RTLNAME="mul_32s_7s_32_1_1_U49" SOURCE="d2.cpp:49" VARIABLE="mul_ln49" MODULE="fiat_25519_carry_mul_Pipeline_VITIS_LOOP_36_1" LOOP="VITIS_LOOP_36_1" BUNDLEDNAME="" DSP="2" BRAM="0" URAM="0"/>
	<BindNode BINDTYPE="op" DISPLAY="bind_op mul" ID="" IMPL="auto" LATENCY="0" OPTYPE="mul" PRAGMA="" RTLNAME="mul_32ns_32ns_64_1_1_U25" SOURCE="d2.cpp:49" VARIABLE="mul_ln49_1" MODULE="fiat_25519_carry_mul_Pipeline_VITIS_LOOP_36_1" LOOP="VITIS_LOOP_36_1" BUNDLEDNAME="" DSP="4" BRAM="0" URAM="0"/>
	<BindNode BINDTYPE="op" DISPLAY="bind_op select" ID="" IMPL="auto_sel" LATENCY="0" OPTYPE="select" PRAGMA="" RTLNAME="select_ln49_1_fu_1134_p3" SOURCE="d2.cpp:49" VARIABLE="select_ln49_1" MODULE="fiat_25519_carry_mul_Pipeline_VITIS_LOOP_36_1" LOOP="VITIS_LOOP_36_1" BUNDLEDNAME="" DSP="0" BRAM="0" URAM="0"/>
	<BindNode BINDTYPE="op" DISPLAY="bind_op and" ID="" IMPL="auto" LATENCY="0" OPTYPE="and" PRAGMA="" RTLNAME="and_ln49_fu_1141_p2" SOURCE="d2.cpp:49" VARIABLE="and_ln49" MODULE="fiat_25519_carry_mul_Pipeline_VITIS_LOOP_36_1" LOOP="VITIS_LOOP_36_1" BUNDLEDNAME="" DSP="0" BRAM="0" URAM="0"/>
	<BindNode BINDTYPE="op" DISPLAY="bind_op add" ID="" IMPL="fabric" LATENCY="0" OPTYPE="add" PRAGMA="" RTLNAME="arr_fu_1147_p2" SOURCE="d2.cpp:49" VARIABLE="arr" MODULE="fiat_25519_carry_mul_Pipeline_VITIS_LOOP_36_1" LOOP="VITIS_LOOP_36_1" BUNDLEDNAME="" DSP="0" BRAM="0" URAM="0"/>
	<BindNode BINDTYPE="op" DISPLAY="bind_op mul" ID="" IMPL="auto" LATENCY="0" OPTYPE="mul" PRAGMA="" RTLNAME="mul_32s_6ns_32_1_1_U58" SOURCE="d2.cpp:49" VARIABLE="mul_ln49_2" MODULE="fiat_25519_carry_mul_Pipeline_VITIS_LOOP_36_1" LOOP="VITIS_LOOP_36_1" BUNDLEDNAME="" DSP="2" BRAM="0" URAM="0"/>
	<BindNode BINDTYPE="op" DISPLAY="bind_op add" ID="" IMPL="fabric" LATENCY="0" OPTYPE="add" PRAGMA="" RTLNAME="add_ln48_1_fu_679_p2" SOURCE="d2.cpp:48" VARIABLE="add_ln48_1" MODULE="fiat_25519_carry_mul_Pipeline_VITIS_LOOP_36_1" LOOP="VITIS_LOOP_36_1" BUNDLEDNAME="" DSP="0" BRAM="0" URAM="0"/>
	<BindNode BINDTYPE="op" DISPLAY="bind_op icmp" ID="" IMPL="auto" LATENCY="0" OPTYPE="icmp" PRAGMA="" RTLNAME="icmp_ln48_1_fu_685_p2" SOURCE="d2.cpp:48" VARIABLE="icmp_ln48_1" MODULE="fiat_25519_carry_mul_Pipeline_VITIS_LOOP_36_1" LOOP="VITIS_LOOP_36_1" BUNDLEDNAME="" DSP="0" BRAM="0" URAM="0"/>
	<BindNode BINDTYPE="op" DISPLAY="bind_op and" ID="" IMPL="auto" LATENCY="0" OPTYPE="and" PRAGMA="" RTLNAME="and_ln48_1_fu_691_p2" SOURCE="d2.cpp:48" VARIABLE="and_ln48_1" MODULE="fiat_25519_carry_mul_Pipeline_VITIS_LOOP_36_1" LOOP="VITIS_LOOP_36_1" BUNDLEDNAME="" DSP="0" BRAM="0" URAM="0"/>
	<BindNode BINDTYPE="op" DISPLAY="bind_op select" ID="" IMPL="auto_sel" LATENCY="0" OPTYPE="select" PRAGMA="" RTLNAME="mul_ln49_3_fu_434_p10" SOURCE="d2.cpp:49" VARIABLE="select_ln49_2" MODULE="fiat_25519_carry_mul_Pipeline_VITIS_LOOP_36_1" LOOP="VITIS_LOOP_36_1" BUNDLEDNAME="" DSP="0" BRAM="0" URAM="0"/>
	<BindNode BINDTYPE="op" DISPLAY="bind_op mul" ID="" IMPL="auto" LATENCY="0" OPTYPE="mul" PRAGMA="" RTLNAME="mul_32s_7s_32_1_1_U50" SOURCE="d2.cpp:49" VARIABLE="mul_ln49_3" MODULE="fiat_25519_carry_mul_Pipeline_VITIS_LOOP_36_1" LOOP="VITIS_LOOP_36_1" BUNDLEDNAME="" DSP="2" BRAM="0" URAM="0"/>
	<BindNode BINDTYPE="op" DISPLAY="bind_op mul" ID="" IMPL="auto" LATENCY="0" OPTYPE="mul" PRAGMA="" RTLNAME="mul_32s_6ns_32_1_1_U59" SOURCE="d2.cpp:49" VARIABLE="mul_ln49_4" MODULE="fiat_25519_carry_mul_Pipeline_VITIS_LOOP_36_1" LOOP="VITIS_LOOP_36_1" BUNDLEDNAME="" DSP="2" BRAM="0" URAM="0"/>
	<BindNode BINDTYPE="op" DISPLAY="bind_op mul" ID="" IMPL="auto" LATENCY="0" OPTYPE="mul" PRAGMA="" RTLNAME="mul_32ns_32ns_64_1_1_U26" SOURCE="d2.cpp:49" VARIABLE="mul_ln49_5" MODULE="fiat_25519_carry_mul_Pipeline_VITIS_LOOP_36_1" LOOP="VITIS_LOOP_36_1" BUNDLEDNAME="" DSP="4" BRAM="0" URAM="0"/>
	<BindNode BINDTYPE="op" DISPLAY="bind_op and" ID="" IMPL="auto" LATENCY="0" OPTYPE="and" PRAGMA="" RTLNAME="and_ln49_1_fu_1166_p2" SOURCE="d2.cpp:49" VARIABLE="and_ln49_1" MODULE="fiat_25519_carry_mul_Pipeline_VITIS_LOOP_36_1" LOOP="VITIS_LOOP_36_1" BUNDLEDNAME="" DSP="0" BRAM="0" URAM="0"/>
	<BindNode BINDTYPE="op" DISPLAY="bind_op mul" ID="" IMPL="auto" LATENCY="0" OPTYPE="mul" PRAGMA="" RTLNAME="mul_32ns_32ns_64_1_1_U27" SOURCE="d2.cpp:49" VARIABLE="mul_ln49_6" MODULE="fiat_25519_carry_mul_Pipeline_VITIS_LOOP_36_1" LOOP="VITIS_LOOP_36_1" BUNDLEDNAME="" DSP="4" BRAM="0" URAM="0"/>
	<BindNode BINDTYPE="op" DISPLAY="bind_op select" ID="" IMPL="auto_sel" LATENCY="0" OPTYPE="select" PRAGMA="" RTLNAME="select_ln49_3_fu_1172_p3" SOURCE="d2.cpp:49" VARIABLE="select_ln49_3" MODULE="fiat_25519_carry_mul_Pipeline_VITIS_LOOP_36_1" LOOP="VITIS_LOOP_36_1" BUNDLEDNAME="" DSP="0" BRAM="0" URAM="0"/>
	<BindNode BINDTYPE="op" DISPLAY="bind_op and" ID="" IMPL="auto" LATENCY="0" OPTYPE="and" PRAGMA="" RTLNAME="and_ln49_2_fu_1179_p2" SOURCE="d2.cpp:49" VARIABLE="and_ln49_2" MODULE="fiat_25519_carry_mul_Pipeline_VITIS_LOOP_36_1" LOOP="VITIS_LOOP_36_1" BUNDLEDNAME="" DSP="0" BRAM="0" URAM="0"/>
	<BindNode BINDTYPE="op" DISPLAY="bind_op all" ID="" IMPL="tadder" LATENCY="0" OPTYPE="all" PRAGMA="" RTLNAME="add_ln49_fu_1185_p2" SOURCE="d2.cpp:49" VARIABLE="add_ln49" MODULE="fiat_25519_carry_mul_Pipeline_VITIS_LOOP_36_1" LOOP="VITIS_LOOP_36_1" BUNDLEDNAME="" DSP="0" BRAM="0" URAM="0"/>
	<BindNode BINDTYPE="op" DISPLAY="bind_op all" ID="" IMPL="tadder" LATENCY="0" OPTYPE="all" PRAGMA="" RTLNAME="arr_18_fu_1191_p2" SOURCE="d2.cpp:49" VARIABLE="arr_18" MODULE="fiat_25519_carry_mul_Pipeline_VITIS_LOOP_36_1" LOOP="VITIS_LOOP_36_1" BUNDLEDNAME="" DSP="0" BRAM="0" URAM="0"/>
	<BindNode BINDTYPE="op" DISPLAY="bind_op add" ID="" IMPL="fabric" LATENCY="0" OPTYPE="add" PRAGMA="" RTLNAME="add_ln48_2_fu_706_p2" SOURCE="d2.cpp:48" VARIABLE="add_ln48_2" MODULE="fiat_25519_carry_mul_Pipeline_VITIS_LOOP_36_1" LOOP="VITIS_LOOP_36_1" BUNDLEDNAME="" DSP="0" BRAM="0" URAM="0"/>
	<BindNode BINDTYPE="op" DISPLAY="bind_op icmp" ID="" IMPL="auto" LATENCY="0" OPTYPE="icmp" PRAGMA="" RTLNAME="icmp_ln48_2_fu_712_p2" SOURCE="d2.cpp:48" VARIABLE="icmp_ln48_2" MODULE="fiat_25519_carry_mul_Pipeline_VITIS_LOOP_36_1" LOOP="VITIS_LOOP_36_1" BUNDLEDNAME="" DSP="0" BRAM="0" URAM="0"/>
	<BindNode BINDTYPE="op" DISPLAY="bind_op and" ID="" IMPL="auto" LATENCY="0" OPTYPE="and" PRAGMA="" RTLNAME="and_ln48_2_fu_718_p2" SOURCE="d2.cpp:48" VARIABLE="and_ln48_2" MODULE="fiat_25519_carry_mul_Pipeline_VITIS_LOOP_36_1" LOOP="VITIS_LOOP_36_1" BUNDLEDNAME="" DSP="0" BRAM="0" URAM="0"/>
	<BindNode BINDTYPE="op" DISPLAY="bind_op select" ID="" IMPL="auto_sel" LATENCY="0" OPTYPE="select" PRAGMA="" RTLNAME="mul_ln49_7_fu_439_p10" SOURCE="d2.cpp:49" VARIABLE="select_ln49_4" MODULE="fiat_25519_carry_mul_Pipeline_VITIS_LOOP_36_1" LOOP="VITIS_LOOP_36_1" BUNDLEDNAME="" DSP="0" BRAM="0" URAM="0"/>
	<BindNode BINDTYPE="op" DISPLAY="bind_op sub" ID="" IMPL="fabric" LATENCY="0" OPTYPE="sub" PRAGMA="" RTLNAME="tmp_5_fu_739_p11" SOURCE="d2.cpp:49" VARIABLE="sub_ln49" MODULE="fiat_25519_carry_mul_Pipeline_VITIS_LOOP_36_1" LOOP="VITIS_LOOP_36_1" BUNDLEDNAME="" DSP="0" BRAM="0" URAM="0"/>
	<BindNode BINDTYPE="op" DISPLAY="bind_op mux" ID="" IMPL="auto" LATENCY="0" OPTYPE="mux" PRAGMA="" RTLNAME="mux_10_4_32_1_1_U69" SOURCE="d2.cpp:49" VARIABLE="tmp_5" MODULE="fiat_25519_carry_mul_Pipeline_VITIS_LOOP_36_1" LOOP="VITIS_LOOP_36_1" BUNDLEDNAME="" DSP="0" BRAM="0" URAM="0"/>
	<BindNode BINDTYPE="op" DISPLAY="bind_op mul" ID="" IMPL="auto" LATENCY="0" OPTYPE="mul" PRAGMA="" RTLNAME="mul_32s_7s_32_1_1_U51" SOURCE="d2.cpp:49" VARIABLE="mul_ln49_7" MODULE="fiat_25519_carry_mul_Pipeline_VITIS_LOOP_36_1" LOOP="VITIS_LOOP_36_1" BUNDLEDNAME="" DSP="2" BRAM="0" URAM="0"/>
	<BindNode BINDTYPE="op" DISPLAY="bind_op mul" ID="" IMPL="auto" LATENCY="0" OPTYPE="mul" PRAGMA="" RTLNAME="mul_32ns_32ns_64_1_1_U28" SOURCE="d2.cpp:49" VARIABLE="mul_ln49_8" MODULE="fiat_25519_carry_mul_Pipeline_VITIS_LOOP_36_1" LOOP="VITIS_LOOP_36_1" BUNDLEDNAME="" DSP="4" BRAM="0" URAM="0"/>
	<BindNode BINDTYPE="op" DISPLAY="bind_op mul" ID="" IMPL="auto" LATENCY="0" OPTYPE="mul" PRAGMA="" RTLNAME="mul_32ns_32ns_64_1_1_U29" SOURCE="d2.cpp:49" VARIABLE="mul_ln49_9" MODULE="fiat_25519_carry_mul_Pipeline_VITIS_LOOP_36_1" LOOP="VITIS_LOOP_36_1" BUNDLEDNAME="" DSP="4" BRAM="0" URAM="0"/>
	<BindNode BINDTYPE="op" DISPLAY="bind_op mul" ID="" IMPL="auto" LATENCY="0" OPTYPE="mul" PRAGMA="" RTLNAME="mul_32ns_32ns_64_1_1_U30" SOURCE="d2.cpp:49" VARIABLE="mul_ln49_10" MODULE="fiat_25519_carry_mul_Pipeline_VITIS_LOOP_36_1" LOOP="VITIS_LOOP_36_1" BUNDLEDNAME="" DSP="4" BRAM="0" URAM="0"/>
	<BindNode BINDTYPE="op" DISPLAY="bind_op select" ID="" IMPL="auto_sel" LATENCY="0" OPTYPE="select" PRAGMA="" RTLNAME="select_ln49_5_fu_1202_p3" SOURCE="d2.cpp:49" VARIABLE="select_ln49_5" MODULE="fiat_25519_carry_mul_Pipeline_VITIS_LOOP_36_1" LOOP="VITIS_LOOP_36_1" BUNDLEDNAME="" DSP="0" BRAM="0" URAM="0"/>
	<BindNode BINDTYPE="op" DISPLAY="bind_op and" ID="" IMPL="auto" LATENCY="0" OPTYPE="and" PRAGMA="" RTLNAME="and_ln49_3_fu_1209_p2" SOURCE="d2.cpp:49" VARIABLE="and_ln49_3" MODULE="fiat_25519_carry_mul_Pipeline_VITIS_LOOP_36_1" LOOP="VITIS_LOOP_36_1" BUNDLEDNAME="" DSP="0" BRAM="0" URAM="0"/>
	<BindNode BINDTYPE="op" DISPLAY="bind_op and" ID="" IMPL="auto" LATENCY="0" OPTYPE="and" PRAGMA="" RTLNAME="and_ln49_4_fu_1215_p2" SOURCE="d2.cpp:49" VARIABLE="and_ln49_4" MODULE="fiat_25519_carry_mul_Pipeline_VITIS_LOOP_36_1" LOOP="VITIS_LOOP_36_1" BUNDLEDNAME="" DSP="0" BRAM="0" URAM="0"/>
	<BindNode BINDTYPE="op" DISPLAY="bind_op and" ID="" IMPL="auto" LATENCY="0" OPTYPE="and" PRAGMA="" RTLNAME="and_ln49_5_fu_1221_p2" SOURCE="d2.cpp:49" VARIABLE="and_ln49_5" MODULE="fiat_25519_carry_mul_Pipeline_VITIS_LOOP_36_1" LOOP="VITIS_LOOP_36_1" BUNDLEDNAME="" DSP="0" BRAM="0" URAM="0"/>
	<BindNode BINDTYPE="op" DISPLAY="bind_op add" ID="" IMPL="fabric" LATENCY="0" OPTYPE="add" PRAGMA="" RTLNAME="add_ln49_2_fu_1227_p2" SOURCE="d2.cpp:49" VARIABLE="add_ln49_2" MODULE="fiat_25519_carry_mul_Pipeline_VITIS_LOOP_36_1" LOOP="VITIS_LOOP_36_1" BUNDLEDNAME="" DSP="0" BRAM="0" URAM="0"/>
	<BindNode BINDTYPE="op" DISPLAY="bind_op all" ID="" IMPL="tadder" LATENCY="0" OPTYPE="all" PRAGMA="" RTLNAME="add_ln49_3_fu_1233_p2" SOURCE="d2.cpp:49" VARIABLE="add_ln49_3" MODULE="fiat_25519_carry_mul_Pipeline_VITIS_LOOP_36_1" LOOP="VITIS_LOOP_36_1" BUNDLEDNAME="" DSP="0" BRAM="0" URAM="0"/>
	<BindNode BINDTYPE="op" DISPLAY="bind_op all" ID="" IMPL="tadder" LATENCY="0" OPTYPE="all" PRAGMA="" RTLNAME="arr_19_fu_1239_p2" SOURCE="d2.cpp:49" VARIABLE="arr_19" MODULE="fiat_25519_carry_mul_Pipeline_VITIS_LOOP_36_1" LOOP="VITIS_LOOP_36_1" BUNDLEDNAME="" DSP="0" BRAM="0" URAM="0"/>
	<BindNode BINDTYPE="op" DISPLAY="bind_op mul" ID="" IMPL="auto" LATENCY="0" OPTYPE="mul" PRAGMA="" RTLNAME="mul_32s_6ns_32_1_1_U60" SOURCE="d2.cpp:49" VARIABLE="mul_ln49_11" MODULE="fiat_25519_carry_mul_Pipeline_VITIS_LOOP_36_1" LOOP="VITIS_LOOP_36_1" BUNDLEDNAME="" DSP="2" BRAM="0" URAM="0"/>
	<BindNode BINDTYPE="op" DISPLAY="bind_op add" ID="" IMPL="fabric" LATENCY="0" OPTYPE="add" PRAGMA="" RTLNAME="add_ln48_3_fu_767_p2" SOURCE="d2.cpp:48" VARIABLE="add_ln48_3" MODULE="fiat_25519_carry_mul_Pipeline_VITIS_LOOP_36_1" LOOP="VITIS_LOOP_36_1" BUNDLEDNAME="" DSP="0" BRAM="0" URAM="0"/>
	<BindNode BINDTYPE="op" DISPLAY="bind_op icmp" ID="" IMPL="auto" LATENCY="0" OPTYPE="icmp" PRAGMA="" RTLNAME="icmp_ln48_3_fu_773_p2" SOURCE="d2.cpp:48" VARIABLE="icmp_ln48_3" MODULE="fiat_25519_carry_mul_Pipeline_VITIS_LOOP_36_1" LOOP="VITIS_LOOP_36_1" BUNDLEDNAME="" DSP="0" BRAM="0" URAM="0"/>
	<BindNode BINDTYPE="op" DISPLAY="bind_op and" ID="" IMPL="auto" LATENCY="0" OPTYPE="and" PRAGMA="" RTLNAME="and_ln48_3_fu_779_p2" SOURCE="d2.cpp:48" VARIABLE="and_ln48_3" MODULE="fiat_25519_carry_mul_Pipeline_VITIS_LOOP_36_1" LOOP="VITIS_LOOP_36_1" BUNDLEDNAME="" DSP="0" BRAM="0" URAM="0"/>
	<BindNode BINDTYPE="op" DISPLAY="bind_op select" ID="" IMPL="auto_sel" LATENCY="0" OPTYPE="select" PRAGMA="" RTLNAME="mul_ln49_12_fu_443_p10" SOURCE="d2.cpp:49" VARIABLE="select_ln49_6" MODULE="fiat_25519_carry_mul_Pipeline_VITIS_LOOP_36_1" LOOP="VITIS_LOOP_36_1" BUNDLEDNAME="" DSP="0" BRAM="0" URAM="0"/>
	<BindNode BINDTYPE="op" DISPLAY="bind_op sub" ID="" IMPL="fabric" LATENCY="0" OPTYPE="sub" PRAGMA="" RTLNAME="tmp_6_fu_800_p11" SOURCE="d2.cpp:49" VARIABLE="sub_ln49_1" MODULE="fiat_25519_carry_mul_Pipeline_VITIS_LOOP_36_1" LOOP="VITIS_LOOP_36_1" BUNDLEDNAME="" DSP="0" BRAM="0" URAM="0"/>
	<BindNode BINDTYPE="op" DISPLAY="bind_op mux" ID="" IMPL="auto" LATENCY="0" OPTYPE="mux" PRAGMA="" RTLNAME="mux_10_4_32_1_1_U70" SOURCE="d2.cpp:49" VARIABLE="tmp_6" MODULE="fiat_25519_carry_mul_Pipeline_VITIS_LOOP_36_1" LOOP="VITIS_LOOP_36_1" BUNDLEDNAME="" DSP="0" BRAM="0" URAM="0"/>
	<BindNode BINDTYPE="op" DISPLAY="bind_op mul" ID="" IMPL="auto" LATENCY="0" OPTYPE="mul" PRAGMA="" RTLNAME="mul_32s_7s_32_1_1_U52" SOURCE="d2.cpp:49" VARIABLE="mul_ln49_12" MODULE="fiat_25519_carry_mul_Pipeline_VITIS_LOOP_36_1" LOOP="VITIS_LOOP_36_1" BUNDLEDNAME="" DSP="2" BRAM="0" URAM="0"/>
	<BindNode BINDTYPE="op" DISPLAY="bind_op mul" ID="" IMPL="auto" LATENCY="0" OPTYPE="mul" PRAGMA="" RTLNAME="mul_32s_6ns_32_1_1_U61" SOURCE="d2.cpp:49" VARIABLE="mul_ln49_13" MODULE="fiat_25519_carry_mul_Pipeline_VITIS_LOOP_36_1" LOOP="VITIS_LOOP_36_1" BUNDLEDNAME="" DSP="2" BRAM="0" URAM="0"/>
	<BindNode BINDTYPE="op" DISPLAY="bind_op mul" ID="" IMPL="auto" LATENCY="0" OPTYPE="mul" PRAGMA="" RTLNAME="mul_32ns_32ns_64_1_1_U31" SOURCE="d2.cpp:49" VARIABLE="mul_ln49_14" MODULE="fiat_25519_carry_mul_Pipeline_VITIS_LOOP_36_1" LOOP="VITIS_LOOP_36_1" BUNDLEDNAME="" DSP="4" BRAM="0" URAM="0"/>
	<BindNode BINDTYPE="op" DISPLAY="bind_op mul" ID="" IMPL="auto" LATENCY="0" OPTYPE="mul" PRAGMA="" RTLNAME="mul_32ns_32ns_64_1_1_U32" SOURCE="d2.cpp:49" VARIABLE="mul_ln49_15" MODULE="fiat_25519_carry_mul_Pipeline_VITIS_LOOP_36_1" LOOP="VITIS_LOOP_36_1" BUNDLEDNAME="" DSP="4" BRAM="0" URAM="0"/>
	<BindNode BINDTYPE="op" DISPLAY="bind_op mul" ID="" IMPL="auto" LATENCY="0" OPTYPE="mul" PRAGMA="" RTLNAME="mul_32ns_32ns_64_1_1_U33" SOURCE="d2.cpp:49" VARIABLE="mul_ln49_16" MODULE="fiat_25519_carry_mul_Pipeline_VITIS_LOOP_36_1" LOOP="VITIS_LOOP_36_1" BUNDLEDNAME="" DSP="4" BRAM="0" URAM="0"/>
	<BindNode BINDTYPE="op" DISPLAY="bind_op select" ID="" IMPL="auto_sel" LATENCY="0" OPTYPE="select" PRAGMA="" RTLNAME="select_ln49_7_fu_1258_p3" SOURCE="d2.cpp:49" VARIABLE="select_ln49_7" MODULE="fiat_25519_carry_mul_Pipeline_VITIS_LOOP_36_1" LOOP="VITIS_LOOP_36_1" BUNDLEDNAME="" DSP="0" BRAM="0" URAM="0"/>
	<BindNode BINDTYPE="op" DISPLAY="bind_op and" ID="" IMPL="auto" LATENCY="0" OPTYPE="and" PRAGMA="" RTLNAME="and_ln49_6_fu_1265_p2" SOURCE="d2.cpp:49" VARIABLE="and_ln49_6" MODULE="fiat_25519_carry_mul_Pipeline_VITIS_LOOP_36_1" LOOP="VITIS_LOOP_36_1" BUNDLEDNAME="" DSP="0" BRAM="0" URAM="0"/>
	<BindNode BINDTYPE="op" DISPLAY="bind_op and" ID="" IMPL="auto" LATENCY="0" OPTYPE="and" PRAGMA="" RTLNAME="and_ln49_7_fu_1271_p2" SOURCE="d2.cpp:49" VARIABLE="and_ln49_7" MODULE="fiat_25519_carry_mul_Pipeline_VITIS_LOOP_36_1" LOOP="VITIS_LOOP_36_1" BUNDLEDNAME="" DSP="0" BRAM="0" URAM="0"/>
	<BindNode BINDTYPE="op" DISPLAY="bind_op and" ID="" IMPL="auto" LATENCY="0" OPTYPE="and" PRAGMA="" RTLNAME="and_ln49_8_fu_1277_p2" SOURCE="d2.cpp:49" VARIABLE="and_ln49_8" MODULE="fiat_25519_carry_mul_Pipeline_VITIS_LOOP_36_1" LOOP="VITIS_LOOP_36_1" BUNDLEDNAME="" DSP="0" BRAM="0" URAM="0"/>
	<BindNode BINDTYPE="op" DISPLAY="bind_op add" ID="" IMPL="fabric" LATENCY="0" OPTYPE="add" PRAGMA="" RTLNAME="add_ln49_5_fu_1283_p2" SOURCE="d2.cpp:49" VARIABLE="add_ln49_5" MODULE="fiat_25519_carry_mul_Pipeline_VITIS_LOOP_36_1" LOOP="VITIS_LOOP_36_1" BUNDLEDNAME="" DSP="0" BRAM="0" URAM="0"/>
	<BindNode BINDTYPE="op" DISPLAY="bind_op all" ID="" IMPL="tadder" LATENCY="0" OPTYPE="all" PRAGMA="" RTLNAME="add_ln49_6_fu_1289_p2" SOURCE="d2.cpp:49" VARIABLE="add_ln49_6" MODULE="fiat_25519_carry_mul_Pipeline_VITIS_LOOP_36_1" LOOP="VITIS_LOOP_36_1" BUNDLEDNAME="" DSP="0" BRAM="0" URAM="0"/>
	<BindNode BINDTYPE="op" DISPLAY="bind_op all" ID="" IMPL="tadder" LATENCY="0" OPTYPE="all" PRAGMA="" RTLNAME="arr_20_fu_1295_p2" SOURCE="d2.cpp:49" VARIABLE="arr_20" MODULE="fiat_25519_carry_mul_Pipeline_VITIS_LOOP_36_1" LOOP="VITIS_LOOP_36_1" BUNDLEDNAME="" DSP="0" BRAM="0" URAM="0"/>
	<BindNode BINDTYPE="op" DISPLAY="bind_op add" ID="" IMPL="fabric" LATENCY="0" OPTYPE="add" PRAGMA="" RTLNAME="add_ln48_4_fu_828_p2" SOURCE="d2.cpp:48" VARIABLE="add_ln48_4" MODULE="fiat_25519_carry_mul_Pipeline_VITIS_LOOP_36_1" LOOP="VITIS_LOOP_36_1" BUNDLEDNAME="" DSP="0" BRAM="0" URAM="0"/>
	<BindNode BINDTYPE="op" DISPLAY="bind_op icmp" ID="" IMPL="auto" LATENCY="0" OPTYPE="icmp" PRAGMA="" RTLNAME="icmp_ln48_4_fu_834_p2" SOURCE="d2.cpp:48" VARIABLE="icmp_ln48_4" MODULE="fiat_25519_carry_mul_Pipeline_VITIS_LOOP_36_1" LOOP="VITIS_LOOP_36_1" BUNDLEDNAME="" DSP="0" BRAM="0" URAM="0"/>
	<BindNode BINDTYPE="op" DISPLAY="bind_op and" ID="" IMPL="auto" LATENCY="0" OPTYPE="and" PRAGMA="" RTLNAME="and_ln48_4_fu_840_p2" SOURCE="d2.cpp:48" VARIABLE="and_ln48_4" MODULE="fiat_25519_carry_mul_Pipeline_VITIS_LOOP_36_1" LOOP="VITIS_LOOP_36_1" BUNDLEDNAME="" DSP="0" BRAM="0" URAM="0"/>
	<BindNode BINDTYPE="op" DISPLAY="bind_op select" ID="" IMPL="auto_sel" LATENCY="0" OPTYPE="select" PRAGMA="" RTLNAME="mul_ln49_17_fu_447_p10" SOURCE="d2.cpp:49" VARIABLE="select_ln49_8" MODULE="fiat_25519_carry_mul_Pipeline_VITIS_LOOP_36_1" LOOP="VITIS_LOOP_36_1" BUNDLEDNAME="" DSP="0" BRAM="0" URAM="0"/>
	<BindNode BINDTYPE="op" DISPLAY="bind_op sub" ID="" IMPL="fabric" LATENCY="0" OPTYPE="sub" PRAGMA="" RTLNAME="tmp_7_fu_861_p11" SOURCE="d2.cpp:49" VARIABLE="sub_ln49_2" MODULE="fiat_25519_carry_mul_Pipeline_VITIS_LOOP_36_1" LOOP="VITIS_LOOP_36_1" BUNDLEDNAME="" DSP="0" BRAM="0" URAM="0"/>
	<BindNode BINDTYPE="op" DISPLAY="bind_op mux" ID="" IMPL="auto" LATENCY="0" OPTYPE="mux" PRAGMA="" RTLNAME="mux_10_4_32_1_1_U71" SOURCE="d2.cpp:49" VARIABLE="tmp_7" MODULE="fiat_25519_carry_mul_Pipeline_VITIS_LOOP_36_1" LOOP="VITIS_LOOP_36_1" BUNDLEDNAME="" DSP="0" BRAM="0" URAM="0"/>
	<BindNode BINDTYPE="op" DISPLAY="bind_op mul" ID="" IMPL="auto" LATENCY="0" OPTYPE="mul" PRAGMA="" RTLNAME="mul_32s_7s_32_1_1_U53" SOURCE="d2.cpp:49" VARIABLE="mul_ln49_17" MODULE="fiat_25519_carry_mul_Pipeline_VITIS_LOOP_36_1" LOOP="VITIS_LOOP_36_1" BUNDLEDNAME="" DSP="2" BRAM="0" URAM="0"/>
	<BindNode BINDTYPE="op" DISPLAY="bind_op mul" ID="" IMPL="auto" LATENCY="0" OPTYPE="mul" PRAGMA="" RTLNAME="mul_32ns_32ns_64_1_1_U34" SOURCE="d2.cpp:49" VARIABLE="mul_ln49_18" MODULE="fiat_25519_carry_mul_Pipeline_VITIS_LOOP_36_1" LOOP="VITIS_LOOP_36_1" BUNDLEDNAME="" DSP="4" BRAM="0" URAM="0"/>
	<BindNode BINDTYPE="op" DISPLAY="bind_op mul" ID="" IMPL="auto" LATENCY="0" OPTYPE="mul" PRAGMA="" RTLNAME="mul_32ns_32ns_64_1_1_U35" SOURCE="d2.cpp:49" VARIABLE="mul_ln49_19" MODULE="fiat_25519_carry_mul_Pipeline_VITIS_LOOP_36_1" LOOP="VITIS_LOOP_36_1" BUNDLEDNAME="" DSP="4" BRAM="0" URAM="0"/>
	<BindNode BINDTYPE="op" DISPLAY="bind_op mul" ID="" IMPL="auto" LATENCY="0" OPTYPE="mul" PRAGMA="" RTLNAME="mul_32ns_32ns_64_1_1_U36" SOURCE="d2.cpp:49" VARIABLE="mul_ln49_20" MODULE="fiat_25519_carry_mul_Pipeline_VITIS_LOOP_36_1" LOOP="VITIS_LOOP_36_1" BUNDLEDNAME="" DSP="4" BRAM="0" URAM="0"/>
	<BindNode BINDTYPE="op" DISPLAY="bind_op select" ID="" IMPL="auto_sel" LATENCY="0" OPTYPE="select" PRAGMA="" RTLNAME="select_ln49_9_fu_1306_p3" SOURCE="d2.cpp:49" VARIABLE="select_ln49_9" MODULE="fiat_25519_carry_mul_Pipeline_VITIS_LOOP_36_1" LOOP="VITIS_LOOP_36_1" BUNDLEDNAME="" DSP="0" BRAM="0" URAM="0"/>
	<BindNode BINDTYPE="op" DISPLAY="bind_op and" ID="" IMPL="auto" LATENCY="0" OPTYPE="and" PRAGMA="" RTLNAME="and_ln49_9_fu_1313_p2" SOURCE="d2.cpp:49" VARIABLE="and_ln49_9" MODULE="fiat_25519_carry_mul_Pipeline_VITIS_LOOP_36_1" LOOP="VITIS_LOOP_36_1" BUNDLEDNAME="" DSP="0" BRAM="0" URAM="0"/>
	<BindNode BINDTYPE="op" DISPLAY="bind_op and" ID="" IMPL="auto" LATENCY="0" OPTYPE="and" PRAGMA="" RTLNAME="and_ln49_10_fu_1319_p2" SOURCE="d2.cpp:49" VARIABLE="and_ln49_10" MODULE="fiat_25519_carry_mul_Pipeline_VITIS_LOOP_36_1" LOOP="VITIS_LOOP_36_1" BUNDLEDNAME="" DSP="0" BRAM="0" URAM="0"/>
	<BindNode BINDTYPE="op" DISPLAY="bind_op and" ID="" IMPL="auto" LATENCY="0" OPTYPE="and" PRAGMA="" RTLNAME="and_ln49_11_fu_1325_p2" SOURCE="d2.cpp:49" VARIABLE="and_ln49_11" MODULE="fiat_25519_carry_mul_Pipeline_VITIS_LOOP_36_1" LOOP="VITIS_LOOP_36_1" BUNDLEDNAME="" DSP="0" BRAM="0" URAM="0"/>
	<BindNode BINDTYPE="op" DISPLAY="bind_op add" ID="" IMPL="fabric" LATENCY="0" OPTYPE="add" PRAGMA="" RTLNAME="add_ln49_8_fu_1331_p2" SOURCE="d2.cpp:49" VARIABLE="add_ln49_8" MODULE="fiat_25519_carry_mul_Pipeline_VITIS_LOOP_36_1" LOOP="VITIS_LOOP_36_1" BUNDLEDNAME="" DSP="0" BRAM="0" URAM="0"/>
	<BindNode BINDTYPE="op" DISPLAY="bind_op all" ID="" IMPL="tadder" LATENCY="0" OPTYPE="all" PRAGMA="" RTLNAME="add_ln49_9_fu_1337_p2" SOURCE="d2.cpp:49" VARIABLE="add_ln49_9" MODULE="fiat_25519_carry_mul_Pipeline_VITIS_LOOP_36_1" LOOP="VITIS_LOOP_36_1" BUNDLEDNAME="" DSP="0" BRAM="0" URAM="0"/>
	<BindNode BINDTYPE="op" DISPLAY="bind_op all" ID="" IMPL="tadder" LATENCY="0" OPTYPE="all" PRAGMA="" RTLNAME="arr_21_fu_1343_p2" SOURCE="d2.cpp:49" VARIABLE="arr_21" MODULE="fiat_25519_carry_mul_Pipeline_VITIS_LOOP_36_1" LOOP="VITIS_LOOP_36_1" BUNDLEDNAME="" DSP="0" BRAM="0" URAM="0"/>
	<BindNode BINDTYPE="op" DISPLAY="bind_op mul" ID="" IMPL="auto" LATENCY="0" OPTYPE="mul" PRAGMA="" RTLNAME="mul_32s_6ns_32_1_1_U62" SOURCE="d2.cpp:49" VARIABLE="mul_ln49_21" MODULE="fiat_25519_carry_mul_Pipeline_VITIS_LOOP_36_1" LOOP="VITIS_LOOP_36_1" BUNDLEDNAME="" DSP="2" BRAM="0" URAM="0"/>
	<BindNode BINDTYPE="op" DISPLAY="bind_op add" ID="" IMPL="fabric" LATENCY="0" OPTYPE="add" PRAGMA="" RTLNAME="add_ln48_5_fu_889_p2" SOURCE="d2.cpp:48" VARIABLE="add_ln48_5" MODULE="fiat_25519_carry_mul_Pipeline_VITIS_LOOP_36_1" LOOP="VITIS_LOOP_36_1" BUNDLEDNAME="" DSP="0" BRAM="0" URAM="0"/>
	<BindNode BINDTYPE="op" DISPLAY="bind_op icmp" ID="" IMPL="auto" LATENCY="0" OPTYPE="icmp" PRAGMA="" RTLNAME="icmp_ln48_5_fu_895_p2" SOURCE="d2.cpp:48" VARIABLE="icmp_ln48_5" MODULE="fiat_25519_carry_mul_Pipeline_VITIS_LOOP_36_1" LOOP="VITIS_LOOP_36_1" BUNDLEDNAME="" DSP="0" BRAM="0" URAM="0"/>
	<BindNode BINDTYPE="op" DISPLAY="bind_op and" ID="" IMPL="auto" LATENCY="0" OPTYPE="and" PRAGMA="" RTLNAME="and_ln48_5_fu_901_p2" SOURCE="d2.cpp:48" VARIABLE="and_ln48_5" MODULE="fiat_25519_carry_mul_Pipeline_VITIS_LOOP_36_1" LOOP="VITIS_LOOP_36_1" BUNDLEDNAME="" DSP="0" BRAM="0" URAM="0"/>
	<BindNode BINDTYPE="op" DISPLAY="bind_op select" ID="" IMPL="auto_sel" LATENCY="0" OPTYPE="select" PRAGMA="" RTLNAME="mul_ln49_22_fu_451_p10" SOURCE="d2.cpp:49" VARIABLE="select_ln49_10" MODULE="fiat_25519_carry_mul_Pipeline_VITIS_LOOP_36_1" LOOP="VITIS_LOOP_36_1" BUNDLEDNAME="" DSP="0" BRAM="0" URAM="0"/>
	<BindNode BINDTYPE="op" DISPLAY="bind_op sub" ID="" IMPL="fabric" LATENCY="0" OPTYPE="sub" PRAGMA="" RTLNAME="tmp_8_fu_922_p11" SOURCE="d2.cpp:49" VARIABLE="sub_ln49_3" MODULE="fiat_25519_carry_mul_Pipeline_VITIS_LOOP_36_1" LOOP="VITIS_LOOP_36_1" BUNDLEDNAME="" DSP="0" BRAM="0" URAM="0"/>
	<BindNode BINDTYPE="op" DISPLAY="bind_op mux" ID="" IMPL="auto" LATENCY="0" OPTYPE="mux" PRAGMA="" RTLNAME="mux_10_4_32_1_1_U72" SOURCE="d2.cpp:49" VARIABLE="tmp_8" MODULE="fiat_25519_carry_mul_Pipeline_VITIS_LOOP_36_1" LOOP="VITIS_LOOP_36_1" BUNDLEDNAME="" DSP="0" BRAM="0" URAM="0"/>
	<BindNode BINDTYPE="op" DISPLAY="bind_op mul" ID="" IMPL="auto" LATENCY="0" OPTYPE="mul" PRAGMA="" RTLNAME="mul_32s_7s_32_1_1_U54" SOURCE="d2.cpp:49" VARIABLE="mul_ln49_22" MODULE="fiat_25519_carry_mul_Pipeline_VITIS_LOOP_36_1" LOOP="VITIS_LOOP_36_1" BUNDLEDNAME="" DSP="2" BRAM="0" URAM="0"/>
	<BindNode BINDTYPE="op" DISPLAY="bind_op mul" ID="" IMPL="auto" LATENCY="0" OPTYPE="mul" PRAGMA="" RTLNAME="mul_32s_6ns_32_1_1_U63" SOURCE="d2.cpp:49" VARIABLE="mul_ln49_23" MODULE="fiat_25519_carry_mul_Pipeline_VITIS_LOOP_36_1" LOOP="VITIS_LOOP_36_1" BUNDLEDNAME="" DSP="2" BRAM="0" URAM="0"/>
	<BindNode BINDTYPE="op" DISPLAY="bind_op mul" ID="" IMPL="auto" LATENCY="0" OPTYPE="mul" PRAGMA="" RTLNAME="mul_32ns_32ns_64_1_1_U37" SOURCE="d2.cpp:49" VARIABLE="mul_ln49_24" MODULE="fiat_25519_carry_mul_Pipeline_VITIS_LOOP_36_1" LOOP="VITIS_LOOP_36_1" BUNDLEDNAME="" DSP="4" BRAM="0" URAM="0"/>
	<BindNode BINDTYPE="op" DISPLAY="bind_op mul" ID="" IMPL="auto" LATENCY="0" OPTYPE="mul" PRAGMA="" RTLNAME="mul_32ns_32ns_64_1_1_U38" SOURCE="d2.cpp:49" VARIABLE="mul_ln49_25" MODULE="fiat_25519_carry_mul_Pipeline_VITIS_LOOP_36_1" LOOP="VITIS_LOOP_36_1" BUNDLEDNAME="" DSP="4" BRAM="0" URAM="0"/>
	<BindNode BINDTYPE="op" DISPLAY="bind_op mul" ID="" IMPL="auto" LATENCY="0" OPTYPE="mul" PRAGMA="" RTLNAME="mul_32ns_32ns_64_1_1_U39" SOURCE="d2.cpp:49" VARIABLE="mul_ln49_26" MODULE="fiat_25519_carry_mul_Pipeline_VITIS_LOOP_36_1" LOOP="VITIS_LOOP_36_1" BUNDLEDNAME="" DSP="4" BRAM="0" URAM="0"/>
	<BindNode BINDTYPE="op" DISPLAY="bind_op select" ID="" IMPL="auto_sel" LATENCY="0" OPTYPE="select" PRAGMA="" RTLNAME="select_ln49_11_fu_1362_p3" SOURCE="d2.cpp:49" VARIABLE="select_ln49_11" MODULE="fiat_25519_carry_mul_Pipeline_VITIS_LOOP_36_1" LOOP="VITIS_LOOP_36_1" BUNDLEDNAME="" DSP="0" BRAM="0" URAM="0"/>
	<BindNode BINDTYPE="op" DISPLAY="bind_op and" ID="" IMPL="auto" LATENCY="0" OPTYPE="and" PRAGMA="" RTLNAME="and_ln49_12_fu_1369_p2" SOURCE="d2.cpp:49" VARIABLE="and_ln49_12" MODULE="fiat_25519_carry_mul_Pipeline_VITIS_LOOP_36_1" LOOP="VITIS_LOOP_36_1" BUNDLEDNAME="" DSP="0" BRAM="0" URAM="0"/>
	<BindNode BINDTYPE="op" DISPLAY="bind_op and" ID="" IMPL="auto" LATENCY="0" OPTYPE="and" PRAGMA="" RTLNAME="and_ln49_13_fu_1375_p2" SOURCE="d2.cpp:49" VARIABLE="and_ln49_13" MODULE="fiat_25519_carry_mul_Pipeline_VITIS_LOOP_36_1" LOOP="VITIS_LOOP_36_1" BUNDLEDNAME="" DSP="0" BRAM="0" URAM="0"/>
	<BindNode BINDTYPE="op" DISPLAY="bind_op and" ID="" IMPL="auto" LATENCY="0" OPTYPE="and" PRAGMA="" RTLNAME="and_ln49_14_fu_1381_p2" SOURCE="d2.cpp:49" VARIABLE="and_ln49_14" MODULE="fiat_25519_carry_mul_Pipeline_VITIS_LOOP_36_1" LOOP="VITIS_LOOP_36_1" BUNDLEDNAME="" DSP="0" BRAM="0" URAM="0"/>
	<BindNode BINDTYPE="op" DISPLAY="bind_op add" ID="" IMPL="fabric" LATENCY="0" OPTYPE="add" PRAGMA="" RTLNAME="add_ln49_11_fu_1387_p2" SOURCE="d2.cpp:49" VARIABLE="add_ln49_11" MODULE="fiat_25519_carry_mul_Pipeline_VITIS_LOOP_36_1" LOOP="VITIS_LOOP_36_1" BUNDLEDNAME="" DSP="0" BRAM="0" URAM="0"/>
	<BindNode BINDTYPE="op" DISPLAY="bind_op all" ID="" IMPL="tadder" LATENCY="0" OPTYPE="all" PRAGMA="" RTLNAME="add_ln49_12_fu_1393_p2" SOURCE="d2.cpp:49" VARIABLE="add_ln49_12" MODULE="fiat_25519_carry_mul_Pipeline_VITIS_LOOP_36_1" LOOP="VITIS_LOOP_36_1" BUNDLEDNAME="" DSP="0" BRAM="0" URAM="0"/>
	<BindNode BINDTYPE="op" DISPLAY="bind_op all" ID="" IMPL="tadder" LATENCY="0" OPTYPE="all" PRAGMA="" RTLNAME="arr_22_fu_1399_p2" SOURCE="d2.cpp:49" VARIABLE="arr_22" MODULE="fiat_25519_carry_mul_Pipeline_VITIS_LOOP_36_1" LOOP="VITIS_LOOP_36_1" BUNDLEDNAME="" DSP="0" BRAM="0" URAM="0"/>
	<BindNode BINDTYPE="op" DISPLAY="bind_op select" ID="" IMPL="auto_sel" LATENCY="0" OPTYPE="select" PRAGMA="" RTLNAME="select_ln49_12_fu_950_p3" SOURCE="d2.cpp:49" VARIABLE="select_ln49_12" MODULE="fiat_25519_carry_mul_Pipeline_VITIS_LOOP_36_1" LOOP="VITIS_LOOP_36_1" BUNDLEDNAME="" DSP="0" BRAM="0" URAM="0"/>
	<BindNode BINDTYPE="op" DISPLAY="bind_op sub" ID="" IMPL="fabric" LATENCY="0" OPTYPE="sub" PRAGMA="" RTLNAME="tmp_9_fu_966_p11" SOURCE="d2.cpp:49" VARIABLE="sub_ln49_4" MODULE="fiat_25519_carry_mul_Pipeline_VITIS_LOOP_36_1" LOOP="VITIS_LOOP_36_1" BUNDLEDNAME="" DSP="0" BRAM="0" URAM="0"/>
	<BindNode BINDTYPE="op" DISPLAY="bind_op mux" ID="" IMPL="auto" LATENCY="0" OPTYPE="mux" PRAGMA="" RTLNAME="mux_10_4_32_1_1_U73" SOURCE="d2.cpp:49" VARIABLE="tmp_9" MODULE="fiat_25519_carry_mul_Pipeline_VITIS_LOOP_36_1" LOOP="VITIS_LOOP_36_1" BUNDLEDNAME="" DSP="0" BRAM="0" URAM="0"/>
	<BindNode BINDTYPE="op" DISPLAY="bind_op mul" ID="" IMPL="auto" LATENCY="0" OPTYPE="mul" PRAGMA="" RTLNAME="mul_32s_7s_32_1_1_U55" SOURCE="d2.cpp:49" VARIABLE="mul_ln49_27" MODULE="fiat_25519_carry_mul_Pipeline_VITIS_LOOP_36_1" LOOP="VITIS_LOOP_36_1" BUNDLEDNAME="" DSP="2" BRAM="0" URAM="0"/>
	<BindNode BINDTYPE="op" DISPLAY="bind_op mul" ID="" IMPL="auto" LATENCY="0" OPTYPE="mul" PRAGMA="" RTLNAME="mul_32ns_32ns_64_1_1_U40" SOURCE="d2.cpp:49" VARIABLE="mul_ln49_28" MODULE="fiat_25519_carry_mul_Pipeline_VITIS_LOOP_36_1" LOOP="VITIS_LOOP_36_1" BUNDLEDNAME="" DSP="4" BRAM="0" URAM="0"/>
	<BindNode BINDTYPE="op" DISPLAY="bind_op mul" ID="" IMPL="auto" LATENCY="0" OPTYPE="mul" PRAGMA="" RTLNAME="mul_32ns_32ns_64_1_1_U41" SOURCE="d2.cpp:49" VARIABLE="mul_ln49_29" MODULE="fiat_25519_carry_mul_Pipeline_VITIS_LOOP_36_1" LOOP="VITIS_LOOP_36_1" BUNDLEDNAME="" DSP="4" BRAM="0" URAM="0"/>
	<BindNode BINDTYPE="op" DISPLAY="bind_op and" ID="" IMPL="auto" LATENCY="0" OPTYPE="and" PRAGMA="" RTLNAME="and_ln49_15_fu_1410_p2" SOURCE="d2.cpp:49" VARIABLE="and_ln49_15" MODULE="fiat_25519_carry_mul_Pipeline_VITIS_LOOP_36_1" LOOP="VITIS_LOOP_36_1" BUNDLEDNAME="" DSP="0" BRAM="0" URAM="0"/>
	<BindNode BINDTYPE="op" DISPLAY="bind_op and" ID="" IMPL="auto" LATENCY="0" OPTYPE="and" PRAGMA="" RTLNAME="and_ln49_16_fu_1416_p2" SOURCE="d2.cpp:49" VARIABLE="and_ln49_16" MODULE="fiat_25519_carry_mul_Pipeline_VITIS_LOOP_36_1" LOOP="VITIS_LOOP_36_1" BUNDLEDNAME="" DSP="0" BRAM="0" URAM="0"/>
	<BindNode BINDTYPE="op" DISPLAY="bind_op mul" ID="" IMPL="auto" LATENCY="0" OPTYPE="mul" PRAGMA="" RTLNAME="mul_32ns_32ns_64_1_1_U42" SOURCE="d2.cpp:49" VARIABLE="mul_ln49_30" MODULE="fiat_25519_carry_mul_Pipeline_VITIS_LOOP_36_1" LOOP="VITIS_LOOP_36_1" BUNDLEDNAME="" DSP="4" BRAM="0" URAM="0"/>
	<BindNode BINDTYPE="op" DISPLAY="bind_op add" ID="" IMPL="fabric" LATENCY="0" OPTYPE="add" PRAGMA="" RTLNAME="add_ln49_14_fu_1422_p2" SOURCE="d2.cpp:49" VARIABLE="add_ln49_14" MODULE="fiat_25519_carry_mul_Pipeline_VITIS_LOOP_36_1" LOOP="VITIS_LOOP_36_1" BUNDLEDNAME="" DSP="0" BRAM="0" URAM="0"/>
	<BindNode BINDTYPE="op" DISPLAY="bind_op all" ID="" IMPL="tadder" LATENCY="0" OPTYPE="all" PRAGMA="" RTLNAME="add_ln49_15_fu_1428_p2" SOURCE="d2.cpp:49" VARIABLE="add_ln49_15" MODULE="fiat_25519_carry_mul_Pipeline_VITIS_LOOP_36_1" LOOP="VITIS_LOOP_36_1" BUNDLEDNAME="" DSP="0" BRAM="0" URAM="0"/>
	<BindNode BINDTYPE="op" DISPLAY="bind_op all" ID="" IMPL="tadder" LATENCY="0" OPTYPE="all" PRAGMA="" RTLNAME="arr_23_fu_1434_p2" SOURCE="d2.cpp:49" VARIABLE="arr_23" MODULE="fiat_25519_carry_mul_Pipeline_VITIS_LOOP_36_1" LOOP="VITIS_LOOP_36_1" BUNDLEDNAME="" DSP="0" BRAM="0" URAM="0"/>
	<BindNode BINDTYPE="op" DISPLAY="bind_op mul" ID="" IMPL="auto" LATENCY="0" OPTYPE="mul" PRAGMA="" RTLNAME="mul_32s_6ns_32_1_1_U64" SOURCE="d2.cpp:49" VARIABLE="mul_ln49_31" MODULE="fiat_25519_carry_mul_Pipeline_VITIS_LOOP_36_1" LOOP="VITIS_LOOP_36_1" BUNDLEDNAME="" DSP="2" BRAM="0" URAM="0"/>
	<BindNode BINDTYPE="op" DISPLAY="bind_op select" ID="" IMPL="auto_sel" LATENCY="0" OPTYPE="select" PRAGMA="" RTLNAME="mul_ln49_32_fu_459_p10" SOURCE="d2.cpp:49" VARIABLE="select_ln49_13" MODULE="fiat_25519_carry_mul_Pipeline_VITIS_LOOP_36_1" LOOP="VITIS_LOOP_36_1" BUNDLEDNAME="" DSP="0" BRAM="0" URAM="0"/>
	<BindNode BINDTYPE="op" DISPLAY="bind_op sub" ID="" IMPL="fabric" LATENCY="0" OPTYPE="sub" PRAGMA="" RTLNAME="tmp_s_fu_1009_p10" SOURCE="d2.cpp:49" VARIABLE="sub_ln49_5" MODULE="fiat_25519_carry_mul_Pipeline_VITIS_LOOP_36_1" LOOP="VITIS_LOOP_36_1" BUNDLEDNAME="" DSP="0" BRAM="0" URAM="0"/>
	<BindNode BINDTYPE="op" DISPLAY="bind_op mux" ID="" IMPL="auto" LATENCY="0" OPTYPE="mux" PRAGMA="" RTLNAME="mux_9_4_32_1_1_U74" SOURCE="d2.cpp:49" VARIABLE="tmp_s" MODULE="fiat_25519_carry_mul_Pipeline_VITIS_LOOP_36_1" LOOP="VITIS_LOOP_36_1" BUNDLEDNAME="" DSP="0" BRAM="0" URAM="0"/>
	<BindNode BINDTYPE="op" DISPLAY="bind_op mul" ID="" IMPL="auto" LATENCY="0" OPTYPE="mul" PRAGMA="" RTLNAME="mul_32s_7s_32_1_1_U56" SOURCE="d2.cpp:49" VARIABLE="mul_ln49_32" MODULE="fiat_25519_carry_mul_Pipeline_VITIS_LOOP_36_1" LOOP="VITIS_LOOP_36_1" BUNDLEDNAME="" DSP="2" BRAM="0" URAM="0"/>
	<BindNode BINDTYPE="op" DISPLAY="bind_op mul" ID="" IMPL="auto" LATENCY="0" OPTYPE="mul" PRAGMA="" RTLNAME="mul_32s_6ns_32_1_1_U65" SOURCE="d2.cpp:49" VARIABLE="mul_ln49_33" MODULE="fiat_25519_carry_mul_Pipeline_VITIS_LOOP_36_1" LOOP="VITIS_LOOP_36_1" BUNDLEDNAME="" DSP="2" BRAM="0" URAM="0"/>
	<BindNode BINDTYPE="op" DISPLAY="bind_op mul" ID="" IMPL="auto" LATENCY="0" OPTYPE="mul" PRAGMA="" RTLNAME="mul_32ns_32ns_64_1_1_U43" SOURCE="d2.cpp:49" VARIABLE="mul_ln49_34" MODULE="fiat_25519_carry_mul_Pipeline_VITIS_LOOP_36_1" LOOP="VITIS_LOOP_36_1" BUNDLEDNAME="" DSP="4" BRAM="0" URAM="0"/>
	<BindNode BINDTYPE="op" DISPLAY="bind_op and" ID="" IMPL="auto" LATENCY="0" OPTYPE="and" PRAGMA="" RTLNAME="and_ln49_17_fu_1452_p2" SOURCE="d2.cpp:49" VARIABLE="and_ln49_17" MODULE="fiat_25519_carry_mul_Pipeline_VITIS_LOOP_36_1" LOOP="VITIS_LOOP_36_1" BUNDLEDNAME="" DSP="0" BRAM="0" URAM="0"/>
	<BindNode BINDTYPE="op" DISPLAY="bind_op mul" ID="" IMPL="auto" LATENCY="0" OPTYPE="mul" PRAGMA="" RTLNAME="mul_32ns_32ns_64_1_1_U44" SOURCE="d2.cpp:49" VARIABLE="mul_ln49_35" MODULE="fiat_25519_carry_mul_Pipeline_VITIS_LOOP_36_1" LOOP="VITIS_LOOP_36_1" BUNDLEDNAME="" DSP="4" BRAM="0" URAM="0"/>
	<BindNode BINDTYPE="op" DISPLAY="bind_op mul" ID="" IMPL="auto" LATENCY="0" OPTYPE="mul" PRAGMA="" RTLNAME="mul_32ns_32ns_64_1_1_U45" SOURCE="d2.cpp:49" VARIABLE="mul_ln49_36" MODULE="fiat_25519_carry_mul_Pipeline_VITIS_LOOP_36_1" LOOP="VITIS_LOOP_36_1" BUNDLEDNAME="" DSP="4" BRAM="0" URAM="0"/>
	<BindNode BINDTYPE="op" DISPLAY="bind_op add" ID="" IMPL="fabric" LATENCY="0" OPTYPE="add" PRAGMA="" RTLNAME="add_ln49_17_fu_1458_p2" SOURCE="d2.cpp:49" VARIABLE="add_ln49_17" MODULE="fiat_25519_carry_mul_Pipeline_VITIS_LOOP_36_1" LOOP="VITIS_LOOP_36_1" BUNDLEDNAME="" DSP="0" BRAM="0" URAM="0"/>
	<BindNode BINDTYPE="op" DISPLAY="bind_op all" ID="" IMPL="tadder" LATENCY="0" OPTYPE="all" PRAGMA="" RTLNAME="add_ln49_18_fu_1464_p2" SOURCE="d2.cpp:49" VARIABLE="add_ln49_18" MODULE="fiat_25519_carry_mul_Pipeline_VITIS_LOOP_36_1" LOOP="VITIS_LOOP_36_1" BUNDLEDNAME="" DSP="0" BRAM="0" URAM="0"/>
	<BindNode BINDTYPE="op" DISPLAY="bind_op all" ID="" IMPL="tadder" LATENCY="0" OPTYPE="all" PRAGMA="" RTLNAME="arr_24_fu_1470_p2" SOURCE="d2.cpp:49" VARIABLE="arr_24" MODULE="fiat_25519_carry_mul_Pipeline_VITIS_LOOP_36_1" LOOP="VITIS_LOOP_36_1" BUNDLEDNAME="" DSP="0" BRAM="0" URAM="0"/>
	<BindNode BINDTYPE="op" DISPLAY="bind_op sub" ID="" IMPL="fabric" LATENCY="0" OPTYPE="sub" PRAGMA="" RTLNAME="tmp_3_fu_1041_p9" SOURCE="d2.cpp:49" VARIABLE="sub_ln49_6" MODULE="fiat_25519_carry_mul_Pipeline_VITIS_LOOP_36_1" LOOP="VITIS_LOOP_36_1" BUNDLEDNAME="" DSP="0" BRAM="0" URAM="0"/>
	<BindNode BINDTYPE="op" DISPLAY="bind_op mux" ID="" IMPL="auto" LATENCY="0" OPTYPE="mux" PRAGMA="" RTLNAME="mux_8_3_32_1_1_U75" SOURCE="d2.cpp:49" VARIABLE="tmp_3" MODULE="fiat_25519_carry_mul_Pipeline_VITIS_LOOP_36_1" LOOP="VITIS_LOOP_36_1" BUNDLEDNAME="" DSP="0" BRAM="0" URAM="0"/>
	<BindNode BINDTYPE="op" DISPLAY="bind_op mul" ID="" IMPL="auto" LATENCY="0" OPTYPE="mul" PRAGMA="" RTLNAME="mul_32s_7s_32_1_1_U57" SOURCE="d2.cpp:49" VARIABLE="mul_ln49_37" MODULE="fiat_25519_carry_mul_Pipeline_VITIS_LOOP_36_1" LOOP="VITIS_LOOP_36_1" BUNDLEDNAME="" DSP="2" BRAM="0" URAM="0"/>
	<BindNode BINDTYPE="op" DISPLAY="bind_op mul" ID="" IMPL="auto" LATENCY="0" OPTYPE="mul" PRAGMA="" RTLNAME="mul_32ns_32ns_64_1_1_U46" SOURCE="d2.cpp:49" VARIABLE="mul_ln49_38" MODULE="fiat_25519_carry_mul_Pipeline_VITIS_LOOP_36_1" LOOP="VITIS_LOOP_36_1" BUNDLEDNAME="" DSP="4" BRAM="0" URAM="0"/>
	<BindNode BINDTYPE="op" DISPLAY="bind_op mul" ID="" IMPL="auto" LATENCY="0" OPTYPE="mul" PRAGMA="" RTLNAME="mul_32ns_32ns_64_1_1_U47" SOURCE="d2.cpp:49" VARIABLE="mul_ln49_39" MODULE="fiat_25519_carry_mul_Pipeline_VITIS_LOOP_36_1" LOOP="VITIS_LOOP_36_1" BUNDLEDNAME="" DSP="4" BRAM="0" URAM="0"/>
	<BindNode BINDTYPE="op" DISPLAY="bind_op mul" ID="" IMPL="auto" LATENCY="0" OPTYPE="mul" PRAGMA="" RTLNAME="mul_32ns_32ns_64_1_1_U48" SOURCE="d2.cpp:49" VARIABLE="mul_ln49_40" MODULE="fiat_25519_carry_mul_Pipeline_VITIS_LOOP_36_1" LOOP="VITIS_LOOP_36_1" BUNDLEDNAME="" DSP="4" BRAM="0" URAM="0"/>
	<BindNode BINDTYPE="op" DISPLAY="bind_op add" ID="" IMPL="fabric" LATENCY="0" OPTYPE="add" PRAGMA="" RTLNAME="add_ln49_20_fu_1480_p2" SOURCE="d2.cpp:49" VARIABLE="add_ln49_20" MODULE="fiat_25519_carry_mul_Pipeline_VITIS_LOOP_36_1" LOOP="VITIS_LOOP_36_1" BUNDLEDNAME="" DSP="0" BRAM="0" URAM="0"/>
	<BindNode BINDTYPE="op" DISPLAY="bind_op all" ID="" IMPL="tadder" LATENCY="0" OPTYPE="all" PRAGMA="" RTLNAME="add_ln49_21_fu_1486_p2" SOURCE="d2.cpp:49" VARIABLE="add_ln49_21" MODULE="fiat_25519_carry_mul_Pipeline_VITIS_LOOP_36_1" LOOP="VITIS_LOOP_36_1" BUNDLEDNAME="" DSP="0" BRAM="0" URAM="0"/>
	<BindNode BINDTYPE="op" DISPLAY="bind_op all" ID="" IMPL="tadder" LATENCY="0" OPTYPE="all" PRAGMA="" RTLNAME="arr_25_fu_1492_p2" SOURCE="d2.cpp:49" VARIABLE="arr_25" MODULE="fiat_25519_carry_mul_Pipeline_VITIS_LOOP_36_1" LOOP="VITIS_LOOP_36_1" BUNDLEDNAME="" DSP="0" BRAM="0" URAM="0"/>
	<BindNode BINDTYPE="op" DISPLAY="bind_op icmp" ID="" IMPL="auto" LATENCY="0" OPTYPE="icmp" PRAGMA="" RTLNAME="icmp_ln67_fu_544_p2" SOURCE="d2.cpp:67" VARIABLE="icmp_ln67" MODULE="fiat_25519_carry_mul_Pipeline_VITIS_LOOP_55_5" LOOP="VITIS_LOOP_55_5" BUNDLEDNAME="" DSP="0" BRAM="0" URAM="0"/>
	<BindNode BINDTYPE="op" DISPLAY="bind_op add" ID="" IMPL="fabric" LATENCY="0" OPTYPE="add" PRAGMA="" RTLNAME="add_ln67_fu_550_p2" SOURCE="d2.cpp:67" VARIABLE="add_ln67" MODULE="fiat_25519_carry_mul_Pipeline_VITIS_LOOP_55_5" LOOP="VITIS_LOOP_55_5" BUNDLEDNAME="" DSP="0" BRAM="0" URAM="0"/>
	<BindNode BINDTYPE="op" DISPLAY="bind_op mux" ID="" IMPL="auto" LATENCY="0" OPTYPE="mux" PRAGMA="" RTLNAME="mux_10_4_32_1_1_x_U119" SOURCE="d2.cpp:68" VARIABLE="tmp_4" MODULE="fiat_25519_carry_mul_Pipeline_VITIS_LOOP_55_5" LOOP="VITIS_LOOP_55_5" BUNDLEDNAME="" DSP="0" BRAM="0" URAM="0"/>
	<BindNode BINDTYPE="op" DISPLAY="bind_op sub" ID="" IMPL="fabric" LATENCY="0" OPTYPE="sub" PRAGMA="" RTLNAME="tmp_s_fu_638_p11" SOURCE="d2.cpp:68" VARIABLE="sub_ln68" MODULE="fiat_25519_carry_mul_Pipeline_VITIS_LOOP_55_5" LOOP="VITIS_LOOP_55_5" BUNDLEDNAME="" DSP="0" BRAM="0" URAM="0"/>
	<BindNode BINDTYPE="op" DISPLAY="bind_op mux" ID="" IMPL="auto" LATENCY="0" OPTYPE="mux" PRAGMA="" RTLNAME="mux_10_4_32_1_1_x_U120" SOURCE="d2.cpp:68" VARIABLE="tmp_s" MODULE="fiat_25519_carry_mul_Pipeline_VITIS_LOOP_55_5" LOOP="VITIS_LOOP_55_5" BUNDLEDNAME="" DSP="0" BRAM="0" URAM="0"/>
	<BindNode BINDTYPE="op" DISPLAY="bind_op mul" ID="" IMPL="auto" LATENCY="0" OPTYPE="mul" PRAGMA="" RTLNAME="mul_32ns_32ns_64_1_1_U109" SOURCE="d2.cpp:68" VARIABLE="mul_ln68" MODULE="fiat_25519_carry_mul_Pipeline_VITIS_LOOP_55_5" LOOP="VITIS_LOOP_55_5" BUNDLEDNAME="" DSP="4" BRAM="0" URAM="0"/>
	<BindNode BINDTYPE="op" DISPLAY="bind_op add" ID="" IMPL="fabric" LATENCY="0" OPTYPE="add" PRAGMA="" RTLNAME="add_ln68_fu_659_p2" SOURCE="d2.cpp:68" VARIABLE="add_ln68" MODULE="fiat_25519_carry_mul_Pipeline_VITIS_LOOP_55_5" LOOP="VITIS_LOOP_55_5" BUNDLEDNAME="" DSP="0" BRAM="0" URAM="0"/>
	<BindNode BINDTYPE="op" DISPLAY="bind_op icmp" ID="" IMPL="auto" LATENCY="0" OPTYPE="icmp" PRAGMA="" RTLNAME="icmp_ln67_1_fu_665_p2" SOURCE="d2.cpp:67" VARIABLE="icmp_ln67_1" MODULE="fiat_25519_carry_mul_Pipeline_VITIS_LOOP_55_5" LOOP="VITIS_LOOP_55_5" BUNDLEDNAME="" DSP="0" BRAM="0" URAM="0"/>
	<BindNode BINDTYPE="op" DISPLAY="bind_op and" ID="" IMPL="auto" LATENCY="0" OPTYPE="and" PRAGMA="" RTLNAME="and_ln67_fu_671_p2" SOURCE="d2.cpp:67" VARIABLE="and_ln67" MODULE="fiat_25519_carry_mul_Pipeline_VITIS_LOOP_55_5" LOOP="VITIS_LOOP_55_5" BUNDLEDNAME="" DSP="0" BRAM="0" URAM="0"/>
	<BindNode BINDTYPE="op" DISPLAY="bind_op sub" ID="" IMPL="fabric" LATENCY="0" OPTYPE="sub" PRAGMA="" RTLNAME="tmp_1_fu_683_p10" SOURCE="d2.cpp:68" VARIABLE="sub_ln68_1" MODULE="fiat_25519_carry_mul_Pipeline_VITIS_LOOP_55_5" LOOP="VITIS_LOOP_55_5" BUNDLEDNAME="" DSP="0" BRAM="0" URAM="0"/>
	<BindNode BINDTYPE="op" DISPLAY="bind_op mux" ID="" IMPL="auto" LATENCY="0" OPTYPE="mux" PRAGMA="" RTLNAME="mux_9_4_32_1_1_x_U121" SOURCE="d2.cpp:68" VARIABLE="tmp_1" MODULE="fiat_25519_carry_mul_Pipeline_VITIS_LOOP_55_5" LOOP="VITIS_LOOP_55_5" BUNDLEDNAME="" DSP="0" BRAM="0" URAM="0"/>
	<BindNode BINDTYPE="op" DISPLAY="bind_op select" ID="" IMPL="auto_sel" LATENCY="0" OPTYPE="select" PRAGMA="" RTLNAME="select_ln68_fu_704_p3" SOURCE="d2.cpp:68" VARIABLE="select_ln68" MODULE="fiat_25519_carry_mul_Pipeline_VITIS_LOOP_55_5" LOOP="VITIS_LOOP_55_5" BUNDLEDNAME="" DSP="0" BRAM="0" URAM="0"/>
	<BindNode BINDTYPE="op" DISPLAY="bind_op mul" ID="" IMPL="auto" LATENCY="0" OPTYPE="mul" PRAGMA="" RTLNAME="mul_32ns_32ns_64_1_1_U110" SOURCE="d2.cpp:68" VARIABLE="mul_ln68_1" MODULE="fiat_25519_carry_mul_Pipeline_VITIS_LOOP_55_5" LOOP="VITIS_LOOP_55_5" BUNDLEDNAME="" DSP="4" BRAM="0" URAM="0"/>
	<BindNode BINDTYPE="op" DISPLAY="bind_op select" ID="" IMPL="auto_sel" LATENCY="0" OPTYPE="select" PRAGMA="" RTLNAME="select_ln68_5_fu_717_p3" SOURCE="d2.cpp:68" VARIABLE="select_ln68_5" MODULE="fiat_25519_carry_mul_Pipeline_VITIS_LOOP_55_5" LOOP="VITIS_LOOP_55_5" BUNDLEDNAME="" DSP="0" BRAM="0" URAM="0"/>
	<BindNode BINDTYPE="op" DISPLAY="bind_op and" ID="" IMPL="auto" LATENCY="0" OPTYPE="and" PRAGMA="" RTLNAME="and_ln68_fu_725_p2" SOURCE="d2.cpp:68" VARIABLE="and_ln68" MODULE="fiat_25519_carry_mul_Pipeline_VITIS_LOOP_55_5" LOOP="VITIS_LOOP_55_5" BUNDLEDNAME="" DSP="0" BRAM="0" URAM="0"/>
	<BindNode BINDTYPE="op" DISPLAY="bind_op add" ID="" IMPL="fabric" LATENCY="0" OPTYPE="add" PRAGMA="" RTLNAME="add_ln68_1_fu_731_p2" SOURCE="d2.cpp:68" VARIABLE="add_ln68_1" MODULE="fiat_25519_carry_mul_Pipeline_VITIS_LOOP_55_5" LOOP="VITIS_LOOP_55_5" BUNDLEDNAME="" DSP="0" BRAM="0" URAM="0"/>
	<BindNode BINDTYPE="op" DISPLAY="bind_op add" ID="" IMPL="fabric" LATENCY="0" OPTYPE="add" PRAGMA="" RTLNAME="empty_23_fu_737_p2" SOURCE="" VARIABLE="empty_23" MODULE="fiat_25519_carry_mul_Pipeline_VITIS_LOOP_55_5" LOOP="VITIS_LOOP_55_5" BUNDLEDNAME="" DSP="0" BRAM="0" URAM="0"/>
	<BindNode BINDTYPE="op" DISPLAY="bind_op xor" ID="" IMPL="auto" LATENCY="0" OPTYPE="xor" PRAGMA="" RTLNAME="tmp_2_fu_749_p9" SOURCE="d2.cpp:68" VARIABLE="xor_ln68" MODULE="fiat_25519_carry_mul_Pipeline_VITIS_LOOP_55_5" LOOP="VITIS_LOOP_55_5" BUNDLEDNAME="" DSP="0" BRAM="0" URAM="0"/>
	<BindNode BINDTYPE="op" DISPLAY="bind_op mux" ID="" IMPL="auto" LATENCY="0" OPTYPE="mux" PRAGMA="" RTLNAME="mux_8_3_32_1_1_U122" SOURCE="d2.cpp:68" VARIABLE="tmp_2" MODULE="fiat_25519_carry_mul_Pipeline_VITIS_LOOP_55_5" LOOP="VITIS_LOOP_55_5" BUNDLEDNAME="" DSP="0" BRAM="0" URAM="0"/>
	<BindNode BINDTYPE="op" DISPLAY="bind_op icmp" ID="" IMPL="auto" LATENCY="0" OPTYPE="icmp" PRAGMA="" RTLNAME="icmp_ln68_fu_768_p2" SOURCE="d2.cpp:68" VARIABLE="icmp_ln68" MODULE="fiat_25519_carry_mul_Pipeline_VITIS_LOOP_55_5" LOOP="VITIS_LOOP_55_5" BUNDLEDNAME="" DSP="0" BRAM="0" URAM="0"/>
	<BindNode BINDTYPE="op" DISPLAY="bind_op mul" ID="" IMPL="auto" LATENCY="0" OPTYPE="mul" PRAGMA="" RTLNAME="mul_32ns_32ns_64_1_1_U111" SOURCE="d2.cpp:68" VARIABLE="mul_ln68_2" MODULE="fiat_25519_carry_mul_Pipeline_VITIS_LOOP_55_5" LOOP="VITIS_LOOP_55_5" BUNDLEDNAME="" DSP="4" BRAM="0" URAM="0"/>
	<BindNode BINDTYPE="op" DISPLAY="bind_op select" ID="" IMPL="auto_sel" LATENCY="0" OPTYPE="select" PRAGMA="" RTLNAME="select_ln68_6_fu_774_p3" SOURCE="d2.cpp:68" VARIABLE="select_ln68_6" MODULE="fiat_25519_carry_mul_Pipeline_VITIS_LOOP_55_5" LOOP="VITIS_LOOP_55_5" BUNDLEDNAME="" DSP="0" BRAM="0" URAM="0"/>
	<BindNode BINDTYPE="op" DISPLAY="bind_op and" ID="" IMPL="auto" LATENCY="0" OPTYPE="and" PRAGMA="" RTLNAME="and_ln68_1_fu_782_p2" SOURCE="d2.cpp:68" VARIABLE="and_ln68_1" MODULE="fiat_25519_carry_mul_Pipeline_VITIS_LOOP_55_5" LOOP="VITIS_LOOP_55_5" BUNDLEDNAME="" DSP="0" BRAM="0" URAM="0"/>
	<BindNode BINDTYPE="op" DISPLAY="bind_op add" ID="" IMPL="fabric" LATENCY="0" OPTYPE="add" PRAGMA="" RTLNAME="add_ln68_2_fu_788_p2" SOURCE="d2.cpp:68" VARIABLE="add_ln68_2" MODULE="fiat_25519_carry_mul_Pipeline_VITIS_LOOP_55_5" LOOP="VITIS_LOOP_55_5" BUNDLEDNAME="" DSP="0" BRAM="0" URAM="0"/>
	<BindNode BINDTYPE="op" DISPLAY="bind_op add" ID="" IMPL="fabric" LATENCY="0" OPTYPE="add" PRAGMA="" RTLNAME="add_ln67_1_fu_794_p2" SOURCE="d2.cpp:67" VARIABLE="add_ln67_1" MODULE="fiat_25519_carry_mul_Pipeline_VITIS_LOOP_55_5" LOOP="VITIS_LOOP_55_5" BUNDLEDNAME="" DSP="0" BRAM="0" URAM="0"/>
	<BindNode BINDTYPE="op" DISPLAY="bind_op icmp" ID="" IMPL="auto" LATENCY="0" OPTYPE="icmp" PRAGMA="" RTLNAME="icmp_ln67_2_fu_800_p2" SOURCE="d2.cpp:67" VARIABLE="icmp_ln67_2" MODULE="fiat_25519_carry_mul_Pipeline_VITIS_LOOP_55_5" LOOP="VITIS_LOOP_55_5" BUNDLEDNAME="" DSP="0" BRAM="0" URAM="0"/>
	<BindNode BINDTYPE="op" DISPLAY="bind_op and" ID="" IMPL="auto" LATENCY="0" OPTYPE="and" PRAGMA="" RTLNAME="and_ln67_1_fu_806_p2" SOURCE="d2.cpp:67" VARIABLE="and_ln67_1" MODULE="fiat_25519_carry_mul_Pipeline_VITIS_LOOP_55_5" LOOP="VITIS_LOOP_55_5" BUNDLEDNAME="" DSP="0" BRAM="0" URAM="0"/>
	<BindNode BINDTYPE="op" DISPLAY="bind_op sub" ID="" IMPL="fabric" LATENCY="0" OPTYPE="sub" PRAGMA="" RTLNAME="tmp_3_fu_818_p8" SOURCE="d2.cpp:68" VARIABLE="sub_ln68_2" MODULE="fiat_25519_carry_mul_Pipeline_VITIS_LOOP_55_5" LOOP="VITIS_LOOP_55_5" BUNDLEDNAME="" DSP="0" BRAM="0" URAM="0"/>
	<BindNode BINDTYPE="op" DISPLAY="bind_op mux" ID="" IMPL="auto" LATENCY="0" OPTYPE="mux" PRAGMA="" RTLNAME="mux_7_3_32_1_1_U123" SOURCE="d2.cpp:68" VARIABLE="tmp_3" MODULE="fiat_25519_carry_mul_Pipeline_VITIS_LOOP_55_5" LOOP="VITIS_LOOP_55_5" BUNDLEDNAME="" DSP="0" BRAM="0" URAM="0"/>
	<BindNode BINDTYPE="op" DISPLAY="bind_op select" ID="" IMPL="auto_sel" LATENCY="0" OPTYPE="select" PRAGMA="" RTLNAME="select_ln68_1_fu_837_p3" SOURCE="d2.cpp:68" VARIABLE="select_ln68_1" MODULE="fiat_25519_carry_mul_Pipeline_VITIS_LOOP_55_5" LOOP="VITIS_LOOP_55_5" BUNDLEDNAME="" DSP="0" BRAM="0" URAM="0"/>
	<BindNode BINDTYPE="op" DISPLAY="bind_op mul" ID="" IMPL="auto" LATENCY="0" OPTYPE="mul" PRAGMA="" RTLNAME="mul_32ns_32ns_64_1_1_U112" SOURCE="d2.cpp:68" VARIABLE="mul_ln68_3" MODULE="fiat_25519_carry_mul_Pipeline_VITIS_LOOP_55_5" LOOP="VITIS_LOOP_55_5" BUNDLEDNAME="" DSP="4" BRAM="0" URAM="0"/>
	<BindNode BINDTYPE="op" DISPLAY="bind_op select" ID="" IMPL="auto_sel" LATENCY="0" OPTYPE="select" PRAGMA="" RTLNAME="select_ln68_7_fu_850_p3" SOURCE="d2.cpp:68" VARIABLE="select_ln68_7" MODULE="fiat_25519_carry_mul_Pipeline_VITIS_LOOP_55_5" LOOP="VITIS_LOOP_55_5" BUNDLEDNAME="" DSP="0" BRAM="0" URAM="0"/>
	<BindNode BINDTYPE="op" DISPLAY="bind_op and" ID="" IMPL="auto" LATENCY="0" OPTYPE="and" PRAGMA="" RTLNAME="and_ln68_2_fu_858_p2" SOURCE="d2.cpp:68" VARIABLE="and_ln68_2" MODULE="fiat_25519_carry_mul_Pipeline_VITIS_LOOP_55_5" LOOP="VITIS_LOOP_55_5" BUNDLEDNAME="" DSP="0" BRAM="0" URAM="0"/>
	<BindNode BINDTYPE="op" DISPLAY="bind_op add" ID="" IMPL="fabric" LATENCY="0" OPTYPE="add" PRAGMA="" RTLNAME="add_ln68_3_fu_864_p2" SOURCE="d2.cpp:68" VARIABLE="add_ln68_3" MODULE="fiat_25519_carry_mul_Pipeline_VITIS_LOOP_55_5" LOOP="VITIS_LOOP_55_5" BUNDLEDNAME="" DSP="0" BRAM="0" URAM="0"/>
	<BindNode BINDTYPE="op" DISPLAY="bind_op add" ID="" IMPL="fabric" LATENCY="0" OPTYPE="add" PRAGMA="" RTLNAME="empty_24_fu_870_p2" SOURCE="" VARIABLE="empty_24" MODULE="fiat_25519_carry_mul_Pipeline_VITIS_LOOP_55_5" LOOP="VITIS_LOOP_55_5" BUNDLEDNAME="" DSP="0" BRAM="0" URAM="0"/>
	<BindNode BINDTYPE="op" DISPLAY="bind_op sub" ID="" IMPL="fabric" LATENCY="0" OPTYPE="sub" PRAGMA="" RTLNAME="tmp_5_fu_882_p7" SOURCE="d2.cpp:68" VARIABLE="sub_ln68_3" MODULE="fiat_25519_carry_mul_Pipeline_VITIS_LOOP_55_5" LOOP="VITIS_LOOP_55_5" BUNDLEDNAME="" DSP="0" BRAM="0" URAM="0"/>
	<BindNode BINDTYPE="op" DISPLAY="bind_op mux" ID="" IMPL="auto" LATENCY="0" OPTYPE="mux" PRAGMA="" RTLNAME="mux_6_3_32_1_1_U124" SOURCE="d2.cpp:68" VARIABLE="tmp_5" MODULE="fiat_25519_carry_mul_Pipeline_VITIS_LOOP_55_5" LOOP="VITIS_LOOP_55_5" BUNDLEDNAME="" DSP="0" BRAM="0" URAM="0"/>
	<BindNode BINDTYPE="op" DISPLAY="bind_op icmp" ID="" IMPL="auto" LATENCY="0" OPTYPE="icmp" PRAGMA="" RTLNAME="icmp_ln68_1_fu_899_p2" SOURCE="d2.cpp:68" VARIABLE="icmp_ln68_1" MODULE="fiat_25519_carry_mul_Pipeline_VITIS_LOOP_55_5" LOOP="VITIS_LOOP_55_5" BUNDLEDNAME="" DSP="0" BRAM="0" URAM="0"/>
	<BindNode BINDTYPE="op" DISPLAY="bind_op mul" ID="" IMPL="auto" LATENCY="0" OPTYPE="mul" PRAGMA="" RTLNAME="mul_32ns_32ns_64_1_1_U113" SOURCE="d2.cpp:68" VARIABLE="mul_ln68_4" MODULE="fiat_25519_carry_mul_Pipeline_VITIS_LOOP_55_5" LOOP="VITIS_LOOP_55_5" BUNDLEDNAME="" DSP="4" BRAM="0" URAM="0"/>
	<BindNode BINDTYPE="op" DISPLAY="bind_op select" ID="" IMPL="auto_sel" LATENCY="0" OPTYPE="select" PRAGMA="" RTLNAME="select_ln68_8_fu_905_p3" SOURCE="d2.cpp:68" VARIABLE="select_ln68_8" MODULE="fiat_25519_carry_mul_Pipeline_VITIS_LOOP_55_5" LOOP="VITIS_LOOP_55_5" BUNDLEDNAME="" DSP="0" BRAM="0" URAM="0"/>
	<BindNode BINDTYPE="op" DISPLAY="bind_op and" ID="" IMPL="auto" LATENCY="0" OPTYPE="and" PRAGMA="" RTLNAME="and_ln68_3_fu_913_p2" SOURCE="d2.cpp:68" VARIABLE="and_ln68_3" MODULE="fiat_25519_carry_mul_Pipeline_VITIS_LOOP_55_5" LOOP="VITIS_LOOP_55_5" BUNDLEDNAME="" DSP="0" BRAM="0" URAM="0"/>
	<BindNode BINDTYPE="op" DISPLAY="bind_op add" ID="" IMPL="fabric" LATENCY="0" OPTYPE="add" PRAGMA="" RTLNAME="add_ln68_4_fu_919_p2" SOURCE="d2.cpp:68" VARIABLE="add_ln68_4" MODULE="fiat_25519_carry_mul_Pipeline_VITIS_LOOP_55_5" LOOP="VITIS_LOOP_55_5" BUNDLEDNAME="" DSP="0" BRAM="0" URAM="0"/>
	<BindNode BINDTYPE="op" DISPLAY="bind_op add" ID="" IMPL="fabric" LATENCY="0" OPTYPE="add" PRAGMA="" RTLNAME="add_ln67_2_fu_925_p2" SOURCE="d2.cpp:67" VARIABLE="add_ln67_2" MODULE="fiat_25519_carry_mul_Pipeline_VITIS_LOOP_55_5" LOOP="VITIS_LOOP_55_5" BUNDLEDNAME="" DSP="0" BRAM="0" URAM="0"/>
	<BindNode BINDTYPE="op" DISPLAY="bind_op icmp" ID="" IMPL="auto" LATENCY="0" OPTYPE="icmp" PRAGMA="" RTLNAME="icmp_ln67_3_fu_931_p2" SOURCE="d2.cpp:67" VARIABLE="icmp_ln67_3" MODULE="fiat_25519_carry_mul_Pipeline_VITIS_LOOP_55_5" LOOP="VITIS_LOOP_55_5" BUNDLEDNAME="" DSP="0" BRAM="0" URAM="0"/>
	<BindNode BINDTYPE="op" DISPLAY="bind_op and" ID="" IMPL="auto" LATENCY="0" OPTYPE="and" PRAGMA="" RTLNAME="and_ln67_2_fu_937_p2" SOURCE="d2.cpp:67" VARIABLE="and_ln67_2" MODULE="fiat_25519_carry_mul_Pipeline_VITIS_LOOP_55_5" LOOP="VITIS_LOOP_55_5" BUNDLEDNAME="" DSP="0" BRAM="0" URAM="0"/>
	<BindNode BINDTYPE="op" DISPLAY="bind_op sub" ID="" IMPL="fabric" LATENCY="0" OPTYPE="sub" PRAGMA="" RTLNAME="tmp_6_fu_949_p6" SOURCE="d2.cpp:68" VARIABLE="sub_ln68_4" MODULE="fiat_25519_carry_mul_Pipeline_VITIS_LOOP_55_5" LOOP="VITIS_LOOP_55_5" BUNDLEDNAME="" DSP="0" BRAM="0" URAM="0"/>
	<BindNode BINDTYPE="op" DISPLAY="bind_op mux" ID="" IMPL="auto" LATENCY="0" OPTYPE="mux" PRAGMA="" RTLNAME="mux_5_3_32_1_1_U125" SOURCE="d2.cpp:68" VARIABLE="tmp_6" MODULE="fiat_25519_carry_mul_Pipeline_VITIS_LOOP_55_5" LOOP="VITIS_LOOP_55_5" BUNDLEDNAME="" DSP="0" BRAM="0" URAM="0"/>
	<BindNode BINDTYPE="op" DISPLAY="bind_op select" ID="" IMPL="auto_sel" LATENCY="0" OPTYPE="select" PRAGMA="" RTLNAME="select_ln68_2_fu_966_p3" SOURCE="d2.cpp:68" VARIABLE="select_ln68_2" MODULE="fiat_25519_carry_mul_Pipeline_VITIS_LOOP_55_5" LOOP="VITIS_LOOP_55_5" BUNDLEDNAME="" DSP="0" BRAM="0" URAM="0"/>
	<BindNode BINDTYPE="op" DISPLAY="bind_op mul" ID="" IMPL="auto" LATENCY="0" OPTYPE="mul" PRAGMA="" RTLNAME="mul_32ns_32ns_64_1_1_U114" SOURCE="d2.cpp:68" VARIABLE="mul_ln68_5" MODULE="fiat_25519_carry_mul_Pipeline_VITIS_LOOP_55_5" LOOP="VITIS_LOOP_55_5" BUNDLEDNAME="" DSP="4" BRAM="0" URAM="0"/>
	<BindNode BINDTYPE="op" DISPLAY="bind_op select" ID="" IMPL="auto_sel" LATENCY="0" OPTYPE="select" PRAGMA="" RTLNAME="select_ln68_9_fu_979_p3" SOURCE="d2.cpp:68" VARIABLE="select_ln68_9" MODULE="fiat_25519_carry_mul_Pipeline_VITIS_LOOP_55_5" LOOP="VITIS_LOOP_55_5" BUNDLEDNAME="" DSP="0" BRAM="0" URAM="0"/>
	<BindNode BINDTYPE="op" DISPLAY="bind_op and" ID="" IMPL="auto" LATENCY="0" OPTYPE="and" PRAGMA="" RTLNAME="and_ln68_4_fu_987_p2" SOURCE="d2.cpp:68" VARIABLE="and_ln68_4" MODULE="fiat_25519_carry_mul_Pipeline_VITIS_LOOP_55_5" LOOP="VITIS_LOOP_55_5" BUNDLEDNAME="" DSP="0" BRAM="0" URAM="0"/>
	<BindNode BINDTYPE="op" DISPLAY="bind_op add" ID="" IMPL="fabric" LATENCY="0" OPTYPE="add" PRAGMA="" RTLNAME="add_ln68_5_fu_993_p2" SOURCE="d2.cpp:68" VARIABLE="add_ln68_5" MODULE="fiat_25519_carry_mul_Pipeline_VITIS_LOOP_55_5" LOOP="VITIS_LOOP_55_5" BUNDLEDNAME="" DSP="0" BRAM="0" URAM="0"/>
	<BindNode BINDTYPE="op" DISPLAY="bind_op add" ID="" IMPL="fabric" LATENCY="0" OPTYPE="add" PRAGMA="" RTLNAME="empty_25_fu_999_p2" SOURCE="" VARIABLE="empty_25" MODULE="fiat_25519_carry_mul_Pipeline_VITIS_LOOP_55_5" LOOP="VITIS_LOOP_55_5" BUNDLEDNAME="" DSP="0" BRAM="0" URAM="0"/>
	<BindNode BINDTYPE="op" DISPLAY="bind_op xor" ID="" IMPL="auto" LATENCY="0" OPTYPE="xor" PRAGMA="" RTLNAME="tmp_7_fu_1011_p5" SOURCE="d2.cpp:68" VARIABLE="xor_ln68_1" MODULE="fiat_25519_carry_mul_Pipeline_VITIS_LOOP_55_5" LOOP="VITIS_LOOP_55_5" BUNDLEDNAME="" DSP="0" BRAM="0" URAM="0"/>
	<BindNode BINDTYPE="op" DISPLAY="bind_op mux" ID="" IMPL="auto" LATENCY="0" OPTYPE="mux" PRAGMA="" RTLNAME="mux_4_2_32_1_1_U126" SOURCE="d2.cpp:68" VARIABLE="tmp_7" MODULE="fiat_25519_carry_mul_Pipeline_VITIS_LOOP_55_5" LOOP="VITIS_LOOP_55_5" BUNDLEDNAME="" DSP="0" BRAM="0" URAM="0"/>
	<BindNode BINDTYPE="op" DISPLAY="bind_op icmp" ID="" IMPL="auto" LATENCY="0" OPTYPE="icmp" PRAGMA="" RTLNAME="icmp_ln68_2_fu_1026_p2" SOURCE="d2.cpp:68" VARIABLE="icmp_ln68_2" MODULE="fiat_25519_carry_mul_Pipeline_VITIS_LOOP_55_5" LOOP="VITIS_LOOP_55_5" BUNDLEDNAME="" DSP="0" BRAM="0" URAM="0"/>
	<BindNode BINDTYPE="op" DISPLAY="bind_op mul" ID="" IMPL="auto" LATENCY="0" OPTYPE="mul" PRAGMA="" RTLNAME="mul_32ns_32ns_64_1_1_U115" SOURCE="d2.cpp:68" VARIABLE="mul_ln68_6" MODULE="fiat_25519_carry_mul_Pipeline_VITIS_LOOP_55_5" LOOP="VITIS_LOOP_55_5" BUNDLEDNAME="" DSP="4" BRAM="0" URAM="0"/>
	<BindNode BINDTYPE="op" DISPLAY="bind_op select" ID="" IMPL="auto_sel" LATENCY="0" OPTYPE="select" PRAGMA="" RTLNAME="select_ln68_10_fu_1032_p3" SOURCE="d2.cpp:68" VARIABLE="select_ln68_10" MODULE="fiat_25519_carry_mul_Pipeline_VITIS_LOOP_55_5" LOOP="VITIS_LOOP_55_5" BUNDLEDNAME="" DSP="0" BRAM="0" URAM="0"/>
	<BindNode BINDTYPE="op" DISPLAY="bind_op and" ID="" IMPL="auto" LATENCY="0" OPTYPE="and" PRAGMA="" RTLNAME="and_ln68_5_fu_1040_p2" SOURCE="d2.cpp:68" VARIABLE="and_ln68_5" MODULE="fiat_25519_carry_mul_Pipeline_VITIS_LOOP_55_5" LOOP="VITIS_LOOP_55_5" BUNDLEDNAME="" DSP="0" BRAM="0" URAM="0"/>
	<BindNode BINDTYPE="op" DISPLAY="bind_op add" ID="" IMPL="fabric" LATENCY="0" OPTYPE="add" PRAGMA="" RTLNAME="add_ln68_6_fu_1046_p2" SOURCE="d2.cpp:68" VARIABLE="add_ln68_6" MODULE="fiat_25519_carry_mul_Pipeline_VITIS_LOOP_55_5" LOOP="VITIS_LOOP_55_5" BUNDLEDNAME="" DSP="0" BRAM="0" URAM="0"/>
	<BindNode BINDTYPE="op" DISPLAY="bind_op add" ID="" IMPL="fabric" LATENCY="0" OPTYPE="add" PRAGMA="" RTLNAME="add_ln67_3_fu_1052_p2" SOURCE="d2.cpp:67" VARIABLE="add_ln67_3" MODULE="fiat_25519_carry_mul_Pipeline_VITIS_LOOP_55_5" LOOP="VITIS_LOOP_55_5" BUNDLEDNAME="" DSP="0" BRAM="0" URAM="0"/>
	<BindNode BINDTYPE="op" DISPLAY="bind_op icmp" ID="" IMPL="auto" LATENCY="0" OPTYPE="icmp" PRAGMA="" RTLNAME="icmp_ln67_4_fu_1058_p2" SOURCE="d2.cpp:67" VARIABLE="icmp_ln67_4" MODULE="fiat_25519_carry_mul_Pipeline_VITIS_LOOP_55_5" LOOP="VITIS_LOOP_55_5" BUNDLEDNAME="" DSP="0" BRAM="0" URAM="0"/>
	<BindNode BINDTYPE="op" DISPLAY="bind_op and" ID="" IMPL="auto" LATENCY="0" OPTYPE="and" PRAGMA="" RTLNAME="and_ln67_3_fu_1064_p2" SOURCE="d2.cpp:67" VARIABLE="and_ln67_3" MODULE="fiat_25519_carry_mul_Pipeline_VITIS_LOOP_55_5" LOOP="VITIS_LOOP_55_5" BUNDLEDNAME="" DSP="0" BRAM="0" URAM="0"/>
	<BindNode BINDTYPE="op" DISPLAY="bind_op sub" ID="" IMPL="fabric" LATENCY="0" OPTYPE="sub" PRAGMA="" RTLNAME="tmp_8_fu_1076_p11" SOURCE="d2.cpp:68" VARIABLE="sub_ln68_5" MODULE="fiat_25519_carry_mul_Pipeline_VITIS_LOOP_55_5" LOOP="VITIS_LOOP_55_5" BUNDLEDNAME="" DSP="0" BRAM="0" URAM="0"/>
	<BindNode BINDTYPE="op" DISPLAY="bind_op mux" ID="" IMPL="auto" LATENCY="0" OPTYPE="mux" PRAGMA="" RTLNAME="mux_10_4_32_1_1_x_U127" SOURCE="d2.cpp:68" VARIABLE="tmp_8" MODULE="fiat_25519_carry_mul_Pipeline_VITIS_LOOP_55_5" LOOP="VITIS_LOOP_55_5" BUNDLEDNAME="" DSP="0" BRAM="0" URAM="0"/>
	<BindNode BINDTYPE="op" DISPLAY="bind_op select" ID="" IMPL="auto_sel" LATENCY="0" OPTYPE="select" PRAGMA="" RTLNAME="select_ln68_3_fu_1104_p3" SOURCE="d2.cpp:68" VARIABLE="select_ln68_3" MODULE="fiat_25519_carry_mul_Pipeline_VITIS_LOOP_55_5" LOOP="VITIS_LOOP_55_5" BUNDLEDNAME="" DSP="0" BRAM="0" URAM="0"/>
	<BindNode BINDTYPE="op" DISPLAY="bind_op mul" ID="" IMPL="auto" LATENCY="0" OPTYPE="mul" PRAGMA="" RTLNAME="mul_32ns_32ns_64_1_1_U116" SOURCE="d2.cpp:68" VARIABLE="mul_ln68_7" MODULE="fiat_25519_carry_mul_Pipeline_VITIS_LOOP_55_5" LOOP="VITIS_LOOP_55_5" BUNDLEDNAME="" DSP="4" BRAM="0" URAM="0"/>
	<BindNode BINDTYPE="op" DISPLAY="bind_op select" ID="" IMPL="auto_sel" LATENCY="0" OPTYPE="select" PRAGMA="" RTLNAME="select_ln68_11_fu_1117_p3" SOURCE="d2.cpp:68" VARIABLE="select_ln68_11" MODULE="fiat_25519_carry_mul_Pipeline_VITIS_LOOP_55_5" LOOP="VITIS_LOOP_55_5" BUNDLEDNAME="" DSP="0" BRAM="0" URAM="0"/>
	<BindNode BINDTYPE="op" DISPLAY="bind_op and" ID="" IMPL="auto" LATENCY="0" OPTYPE="and" PRAGMA="" RTLNAME="and_ln68_6_fu_1125_p2" SOURCE="d2.cpp:68" VARIABLE="and_ln68_6" MODULE="fiat_25519_carry_mul_Pipeline_VITIS_LOOP_55_5" LOOP="VITIS_LOOP_55_5" BUNDLEDNAME="" DSP="0" BRAM="0" URAM="0"/>
	<BindNode BINDTYPE="op" DISPLAY="bind_op add" ID="" IMPL="fabric" LATENCY="0" OPTYPE="add" PRAGMA="" RTLNAME="add_ln68_7_fu_1131_p2" SOURCE="d2.cpp:68" VARIABLE="add_ln68_7" MODULE="fiat_25519_carry_mul_Pipeline_VITIS_LOOP_55_5" LOOP="VITIS_LOOP_55_5" BUNDLEDNAME="" DSP="0" BRAM="0" URAM="0"/>
	<BindNode BINDTYPE="op" DISPLAY="bind_op add" ID="" IMPL="fabric" LATENCY="0" OPTYPE="add" PRAGMA="" RTLNAME="empty_26_fu_1137_p2" SOURCE="d2.cpp:67" VARIABLE="empty_26" MODULE="fiat_25519_carry_mul_Pipeline_VITIS_LOOP_55_5" LOOP="VITIS_LOOP_55_5" BUNDLEDNAME="" DSP="0" BRAM="0" URAM="0"/>
	<BindNode BINDTYPE="op" DISPLAY="bind_op sub" ID="" IMPL="fabric" LATENCY="0" OPTYPE="sub" PRAGMA="" RTLNAME="tmp_9_fu_1149_p11" SOURCE="d2.cpp:68" VARIABLE="sub_ln68_6" MODULE="fiat_25519_carry_mul_Pipeline_VITIS_LOOP_55_5" LOOP="VITIS_LOOP_55_5" BUNDLEDNAME="" DSP="0" BRAM="0" URAM="0"/>
	<BindNode BINDTYPE="op" DISPLAY="bind_op mux" ID="" IMPL="auto" LATENCY="0" OPTYPE="mux" PRAGMA="" RTLNAME="mux_10_4_32_1_1_x_U128" SOURCE="d2.cpp:68" VARIABLE="tmp_9" MODULE="fiat_25519_carry_mul_Pipeline_VITIS_LOOP_55_5" LOOP="VITIS_LOOP_55_5" BUNDLEDNAME="" DSP="0" BRAM="0" URAM="0"/>
	<BindNode BINDTYPE="op" DISPLAY="bind_op icmp" ID="" IMPL="auto" LATENCY="0" OPTYPE="icmp" PRAGMA="" RTLNAME="icmp_ln68_3_fu_1176_p2" SOURCE="d2.cpp:68" VARIABLE="icmp_ln68_3" MODULE="fiat_25519_carry_mul_Pipeline_VITIS_LOOP_55_5" LOOP="VITIS_LOOP_55_5" BUNDLEDNAME="" DSP="0" BRAM="0" URAM="0"/>
	<BindNode BINDTYPE="op" DISPLAY="bind_op mul" ID="" IMPL="auto" LATENCY="0" OPTYPE="mul" PRAGMA="" RTLNAME="mul_32ns_32ns_64_1_1_U117" SOURCE="d2.cpp:68" VARIABLE="mul_ln68_8" MODULE="fiat_25519_carry_mul_Pipeline_VITIS_LOOP_55_5" LOOP="VITIS_LOOP_55_5" BUNDLEDNAME="" DSP="4" BRAM="0" URAM="0"/>
	<BindNode BINDTYPE="op" DISPLAY="bind_op select" ID="" IMPL="auto_sel" LATENCY="0" OPTYPE="select" PRAGMA="" RTLNAME="select_ln68_12_fu_1182_p3" SOURCE="d2.cpp:68" VARIABLE="select_ln68_12" MODULE="fiat_25519_carry_mul_Pipeline_VITIS_LOOP_55_5" LOOP="VITIS_LOOP_55_5" BUNDLEDNAME="" DSP="0" BRAM="0" URAM="0"/>
	<BindNode BINDTYPE="op" DISPLAY="bind_op and" ID="" IMPL="auto" LATENCY="0" OPTYPE="and" PRAGMA="" RTLNAME="and_ln68_7_fu_1190_p2" SOURCE="d2.cpp:68" VARIABLE="and_ln68_7" MODULE="fiat_25519_carry_mul_Pipeline_VITIS_LOOP_55_5" LOOP="VITIS_LOOP_55_5" BUNDLEDNAME="" DSP="0" BRAM="0" URAM="0"/>
	<BindNode BINDTYPE="op" DISPLAY="bind_op add" ID="" IMPL="fabric" LATENCY="0" OPTYPE="add" PRAGMA="" RTLNAME="add_ln68_8_fu_1196_p2" SOURCE="d2.cpp:68" VARIABLE="add_ln68_8" MODULE="fiat_25519_carry_mul_Pipeline_VITIS_LOOP_55_5" LOOP="VITIS_LOOP_55_5" BUNDLEDNAME="" DSP="0" BRAM="0" URAM="0"/>
	<BindNode BINDTYPE="op" DISPLAY="bind_op add" ID="" IMPL="fabric" LATENCY="0" OPTYPE="add" PRAGMA="" RTLNAME="add_ln67_4_fu_1202_p2" SOURCE="d2.cpp:67" VARIABLE="add_ln67_4" MODULE="fiat_25519_carry_mul_Pipeline_VITIS_LOOP_55_5" LOOP="VITIS_LOOP_55_5" BUNDLEDNAME="" DSP="0" BRAM="0" URAM="0"/>
	<BindNode BINDTYPE="op" DISPLAY="bind_op icmp" ID="" IMPL="auto" LATENCY="0" OPTYPE="icmp" PRAGMA="" RTLNAME="icmp_ln67_5_fu_1208_p2" SOURCE="d2.cpp:67" VARIABLE="icmp_ln67_5" MODULE="fiat_25519_carry_mul_Pipeline_VITIS_LOOP_55_5" LOOP="VITIS_LOOP_55_5" BUNDLEDNAME="" DSP="0" BRAM="0" URAM="0"/>
	<BindNode BINDTYPE="op" DISPLAY="bind_op and" ID="" IMPL="auto" LATENCY="0" OPTYPE="and" PRAGMA="" RTLNAME="and_ln67_4_fu_1214_p2" SOURCE="d2.cpp:67" VARIABLE="and_ln67_4" MODULE="fiat_25519_carry_mul_Pipeline_VITIS_LOOP_55_5" LOOP="VITIS_LOOP_55_5" BUNDLEDNAME="" DSP="0" BRAM="0" URAM="0"/>
	<BindNode BINDTYPE="op" DISPLAY="bind_op sub" ID="" IMPL="fabric" LATENCY="0" OPTYPE="sub" PRAGMA="" RTLNAME="tmp_10_fu_1226_p11" SOURCE="d2.cpp:68" VARIABLE="sub_ln68_7" MODULE="fiat_25519_carry_mul_Pipeline_VITIS_LOOP_55_5" LOOP="VITIS_LOOP_55_5" BUNDLEDNAME="" DSP="0" BRAM="0" URAM="0"/>
	<BindNode BINDTYPE="op" DISPLAY="bind_op mux" ID="" IMPL="auto" LATENCY="0" OPTYPE="mux" PRAGMA="" RTLNAME="mux_10_4_32_1_1_x_U129" SOURCE="d2.cpp:68" VARIABLE="tmp_10" MODULE="fiat_25519_carry_mul_Pipeline_VITIS_LOOP_55_5" LOOP="VITIS_LOOP_55_5" BUNDLEDNAME="" DSP="0" BRAM="0" URAM="0"/>
	<BindNode BINDTYPE="op" DISPLAY="bind_op select" ID="" IMPL="auto_sel" LATENCY="0" OPTYPE="select" PRAGMA="" RTLNAME="select_ln68_4_fu_1254_p3" SOURCE="d2.cpp:68" VARIABLE="select_ln68_4" MODULE="fiat_25519_carry_mul_Pipeline_VITIS_LOOP_55_5" LOOP="VITIS_LOOP_55_5" BUNDLEDNAME="" DSP="0" BRAM="0" URAM="0"/>
	<BindNode BINDTYPE="op" DISPLAY="bind_op mul" ID="" IMPL="auto" LATENCY="0" OPTYPE="mul" PRAGMA="" RTLNAME="mul_32ns_32ns_64_1_1_U118" SOURCE="d2.cpp:68" VARIABLE="mul_ln68_9" MODULE="fiat_25519_carry_mul_Pipeline_VITIS_LOOP_55_5" LOOP="VITIS_LOOP_55_5" BUNDLEDNAME="" DSP="4" BRAM="0" URAM="0"/>
	<BindNode BINDTYPE="op" DISPLAY="bind_op select" ID="" IMPL="auto_sel" LATENCY="0" OPTYPE="select" PRAGMA="" RTLNAME="select_ln68_13_fu_1267_p3" SOURCE="d2.cpp:68" VARIABLE="select_ln68_13" MODULE="fiat_25519_carry_mul_Pipeline_VITIS_LOOP_55_5" LOOP="VITIS_LOOP_55_5" BUNDLEDNAME="" DSP="0" BRAM="0" URAM="0"/>
	<BindNode BINDTYPE="op" DISPLAY="bind_op and" ID="" IMPL="auto" LATENCY="0" OPTYPE="and" PRAGMA="" RTLNAME="and_ln68_8_fu_1275_p2" SOURCE="d2.cpp:68" VARIABLE="and_ln68_8" MODULE="fiat_25519_carry_mul_Pipeline_VITIS_LOOP_55_5" LOOP="VITIS_LOOP_55_5" BUNDLEDNAME="" DSP="0" BRAM="0" URAM="0"/>
	<BindNode BINDTYPE="op" DISPLAY="bind_op add" ID="" IMPL="fabric" LATENCY="0" OPTYPE="add" PRAGMA="" RTLNAME="add_ln68_9_fu_1281_p2" SOURCE="d2.cpp:68" VARIABLE="add_ln68_9" MODULE="fiat_25519_carry_mul_Pipeline_VITIS_LOOP_55_5" LOOP="VITIS_LOOP_55_5" BUNDLEDNAME="" DSP="0" BRAM="0" URAM="0"/>
	<BindNode BINDTYPE="op" DISPLAY="bind_op icmp" ID="" IMPL="auto" LATENCY="0" OPTYPE="icmp" PRAGMA="" RTLNAME="icmp_ln87_fu_210_p2" SOURCE="d2.cpp:87" VARIABLE="icmp_ln87" MODULE="fiat_25519_carry_mul_Pipeline_ARRAY_WRITE" LOOP="ARRAY_WRITE" BUNDLEDNAME="" DSP="0" BRAM="0" URAM="0"/>
	<BindNode BINDTYPE="op" DISPLAY="bind_op add" ID="" IMPL="fabric" LATENCY="0" OPTYPE="add" PRAGMA="" RTLNAME="add_ln87_fu_216_p2" SOURCE="d2.cpp:87" VARIABLE="add_ln87" MODULE="fiat_25519_carry_mul_Pipeline_ARRAY_WRITE" LOOP="ARRAY_WRITE" BUNDLEDNAME="" DSP="0" BRAM="0" URAM="0"/>
	<BindNode BINDTYPE="op" DISPLAY="bind_op mux" ID="" IMPL="auto" LATENCY="0" OPTYPE="mux" PRAGMA="" RTLNAME="mux_10_4_27_1_1_U175" SOURCE="d2.cpp:89" VARIABLE="tmp_s" MODULE="fiat_25519_carry_mul_Pipeline_ARRAY_WRITE" LOOP="ARRAY_WRITE" BUNDLEDNAME="" DSP="0" BRAM="0" URAM="0"/>
	<BindNode BINDTYPE="op" DISPLAY="bind_op add" ID="" IMPL="fabric" LATENCY="0" OPTYPE="add" PRAGMA="" RTLNAME="add_ln74_fu_630_p2" SOURCE="d2.cpp:74" VARIABLE="add_ln74" MODULE="fiat_25519_carry_mul" LOOP="" BUNDLEDNAME="" DSP="0" BRAM="0" URAM="0"/>
	<BindNode BINDTYPE="op" DISPLAY="bind_op add" ID="" IMPL="fabric" LATENCY="0" OPTYPE="add" PRAGMA="" RTLNAME="add_ln74_1_fu_664_p2" SOURCE="d2.cpp:74" VARIABLE="add_ln74_1" MODULE="fiat_25519_carry_mul" LOOP="" BUNDLEDNAME="" DSP="0" BRAM="0" URAM="0"/>
	<BindNode BINDTYPE="op" DISPLAY="bind_op add" ID="" IMPL="fabric" LATENCY="0" OPTYPE="add" PRAGMA="" RTLNAME="add_ln74_2_fu_698_p2" SOURCE="d2.cpp:74" VARIABLE="add_ln74_2" MODULE="fiat_25519_carry_mul" LOOP="" BUNDLEDNAME="" DSP="0" BRAM="0" URAM="0"/>
	<BindNode BINDTYPE="op" DISPLAY="bind_op add" ID="" IMPL="fabric" LATENCY="0" OPTYPE="add" PRAGMA="" RTLNAME="add_ln74_3_fu_767_p2" SOURCE="d2.cpp:74" VARIABLE="add_ln74_3" MODULE="fiat_25519_carry_mul" LOOP="" BUNDLEDNAME="" DSP="0" BRAM="0" URAM="0"/>
	<BindNode BINDTYPE="op" DISPLAY="bind_op add" ID="" IMPL="fabric" LATENCY="0" OPTYPE="add" PRAGMA="" RTLNAME="add_ln74_4_fu_801_p2" SOURCE="d2.cpp:74" VARIABLE="add_ln74_4" MODULE="fiat_25519_carry_mul" LOOP="" BUNDLEDNAME="" DSP="0" BRAM="0" URAM="0"/>
	<BindNode BINDTYPE="op" DISPLAY="bind_op add" ID="" IMPL="fabric" LATENCY="0" OPTYPE="add" PRAGMA="" RTLNAME="add_ln74_5_fu_835_p2" SOURCE="d2.cpp:74" VARIABLE="add_ln74_5" MODULE="fiat_25519_carry_mul" LOOP="" BUNDLEDNAME="" DSP="0" BRAM="0" URAM="0"/>
	<BindNode BINDTYPE="op" DISPLAY="bind_op add" ID="" IMPL="fabric" LATENCY="0" OPTYPE="add" PRAGMA="" RTLNAME="add_ln74_6_fu_869_p2" SOURCE="d2.cpp:74" VARIABLE="add_ln74_6" MODULE="fiat_25519_carry_mul" LOOP="" BUNDLEDNAME="" DSP="0" BRAM="0" URAM="0"/>
	<BindNode BINDTYPE="op" DISPLAY="bind_op add" ID="" IMPL="fabric" LATENCY="0" OPTYPE="add" PRAGMA="" RTLNAME="add_ln74_7_fu_903_p2" SOURCE="d2.cpp:74" VARIABLE="add_ln74_7" MODULE="fiat_25519_carry_mul" LOOP="" BUNDLEDNAME="" DSP="0" BRAM="0" URAM="0"/>
	<BindNode BINDTYPE="op" DISPLAY="bind_op add" ID="" IMPL="fabric" LATENCY="0" OPTYPE="add" PRAGMA="" RTLNAME="add_ln74_8_fu_937_p2" SOURCE="d2.cpp:74" VARIABLE="add_ln74_8" MODULE="fiat_25519_carry_mul" LOOP="" BUNDLEDNAME="" DSP="0" BRAM="0" URAM="0"/>
	<BindNode BINDTYPE="op" DISPLAY="bind_op mul" ID="" IMPL="auto" LATENCY="0" OPTYPE="mul" PRAGMA="" RTLNAME="mul_39ns_6ns_44_1_1_U189" SOURCE="d2.cpp:74" VARIABLE="mul_ln74" MODULE="fiat_25519_carry_mul" LOOP="" BUNDLEDNAME="" DSP="2" BRAM="0" URAM="0"/>
	<BindNode BINDTYPE="op" DISPLAY="bind_op add" ID="" IMPL="fabric" LATENCY="0" OPTYPE="add" PRAGMA="" RTLNAME="out1_w_fu_1006_p2" SOURCE="d2.cpp:74" VARIABLE="out1_w" MODULE="fiat_25519_carry_mul" LOOP="" BUNDLEDNAME="" DSP="0" BRAM="0" URAM="0"/>
	<BindNode BINDTYPE="op" DISPLAY="bind_op add" ID="" IMPL="fabric" LATENCY="0" OPTYPE="add" PRAGMA="" RTLNAME="add_ln75_fu_1015_p2" SOURCE="d2.cpp:75" VARIABLE="add_ln75" MODULE="fiat_25519_carry_mul" LOOP="" BUNDLEDNAME="" DSP="0" BRAM="0" URAM="0"/>
	<BindNode BINDTYPE="op" DISPLAY="bind_op add" ID="" IMPL="fabric" LATENCY="0" OPTYPE="add" PRAGMA="" RTLNAME="add_ln75_1_fu_724_p2" SOURCE="d2.cpp:75" VARIABLE="add_ln75_1" MODULE="fiat_25519_carry_mul" LOOP="" BUNDLEDNAME="" DSP="0" BRAM="0" URAM="0"/>
	<BindNode BINDTYPE="op" DISPLAY="bind_op add" ID="" IMPL="fabric" LATENCY="0" OPTYPE="add" PRAGMA="" RTLNAME="out1_w_1_fu_1039_p2" SOURCE="d2.cpp:75" VARIABLE="out1_w_1" MODULE="fiat_25519_carry_mul" LOOP="" BUNDLEDNAME="" DSP="0" BRAM="0" URAM="0"/>
	<BindNode BINDTYPE="op" DISPLAY="bind_op add" ID="" IMPL="fabric" LATENCY="0" OPTYPE="add" PRAGMA="" RTLNAME="add_ln76_fu_1048_p2" SOURCE="d2.cpp:76" VARIABLE="add_ln76" MODULE="fiat_25519_carry_mul" LOOP="" BUNDLEDNAME="" DSP="0" BRAM="0" URAM="0"/>
	<BindNode BINDTYPE="op" DISPLAY="bind_op add" ID="" IMPL="fabric" LATENCY="0" OPTYPE="add" PRAGMA="" RTLNAME="add_ln76_1_fu_730_p2" SOURCE="d2.cpp:76" VARIABLE="add_ln76_1" MODULE="fiat_25519_carry_mul" LOOP="" BUNDLEDNAME="" DSP="0" BRAM="0" URAM="0"/>
	<BindNode BINDTYPE="op" DISPLAY="bind_op add" ID="" IMPL="fabric" LATENCY="0" OPTYPE="add" PRAGMA="" RTLNAME="out1_w_2_fu_1069_p2" SOURCE="d2.cpp:76" VARIABLE="out1_w_2" MODULE="fiat_25519_carry_mul" LOOP="" BUNDLEDNAME="" DSP="0" BRAM="0" URAM="0"/>
	<BindNode BINDTYPE="op" DISPLAY="bind_op add" ID="" IMPL="fabric" LATENCY="0" OPTYPE="add" PRAGMA="" RTLNAME="out1_w_3_fu_736_p2" SOURCE="d2.cpp:77" VARIABLE="out1_w_3" MODULE="fiat_25519_carry_mul" LOOP="" BUNDLEDNAME="" DSP="0" BRAM="0" URAM="0"/>
	<BindNode BINDTYPE="op" DISPLAY="bind_op add" ID="" IMPL="fabric" LATENCY="0" OPTYPE="add" PRAGMA="" RTLNAME="out1_w_4_fu_953_p2" SOURCE="d2.cpp:78" VARIABLE="out1_w_4" MODULE="fiat_25519_carry_mul" LOOP="" BUNDLEDNAME="" DSP="0" BRAM="0" URAM="0"/>
	<BindNode BINDTYPE="op" DISPLAY="bind_op add" ID="" IMPL="fabric" LATENCY="0" OPTYPE="add" PRAGMA="" RTLNAME="out1_w_5_fu_958_p2" SOURCE="d2.cpp:79" VARIABLE="out1_w_5" MODULE="fiat_25519_carry_mul" LOOP="" BUNDLEDNAME="" DSP="0" BRAM="0" URAM="0"/>
	<BindNode BINDTYPE="op" DISPLAY="bind_op add" ID="" IMPL="fabric" LATENCY="0" OPTYPE="add" PRAGMA="" RTLNAME="out1_w_6_fu_964_p2" SOURCE="d2.cpp:80" VARIABLE="out1_w_6" MODULE="fiat_25519_carry_mul" LOOP="" BUNDLEDNAME="" DSP="0" BRAM="0" URAM="0"/>
	<BindNode BINDTYPE="op" DISPLAY="bind_op add" ID="" IMPL="fabric" LATENCY="0" OPTYPE="add" PRAGMA="" RTLNAME="out1_w_7_fu_970_p2" SOURCE="d2.cpp:81" VARIABLE="out1_w_7" MODULE="fiat_25519_carry_mul" LOOP="" BUNDLEDNAME="" DSP="0" BRAM="0" URAM="0"/>
	<BindNode BINDTYPE="op" DISPLAY="bind_op add" ID="" IMPL="fabric" LATENCY="0" OPTYPE="add" PRAGMA="" RTLNAME="out1_w_8_fu_976_p2" SOURCE="d2.cpp:82" VARIABLE="out1_w_8" MODULE="fiat_25519_carry_mul" LOOP="" BUNDLEDNAME="" DSP="0" BRAM="0" URAM="0"/>
	<BindNode BINDTYPE="op" DISPLAY="bind_op add" ID="" IMPL="fabric" LATENCY="0" OPTYPE="add" PRAGMA="" RTLNAME="out1_w_9_fu_982_p2" SOURCE="d2.cpp:83" VARIABLE="out1_w_9" MODULE="fiat_25519_carry_mul" LOOP="" BUNDLEDNAME="" DSP="0" BRAM="0" URAM="0"/>
	<BindNode BINDTYPE="adapter" DISPLAY="bind_adapter axilite" ID="" IMPL="" LATENCY="" OPTYPE="" PRAGMA="yes" RTLNAME="control_s_axi_U" SOURCE="" VARIABLE="" MODULE="fiat_25519_carry_mul" LOOP="" BUNDLEDNAME="control" DSP="0" BRAM="0" URAM="0"/>
	<BindNode BINDTYPE="adapter" DISPLAY="bind_adapter axi_master" ID="" IMPL="" LATENCY="" OPTYPE="" PRAGMA="yes" RTLNAME="mem_m_axi_U" SOURCE="" VARIABLE="" MODULE="fiat_25519_carry_mul" LOOP="" BUNDLEDNAME="mem" DSP="0" BRAM="4" URAM="0"/>
</BindInfo>
