{
    "1": {
        "name": "fiat_25519_carry_mul_Pipeline_ARRAY_1_READ",
        "file": "d5.cpp",
        "fileloc": "0",
        "instructions": "70",
        "total_instructions": "70",
        "calls": "",
        "basicblocks": "15",
        "loads": {
            "L": "11"
        },
        "stores": {
            "L": "12"
        },
        "loops": {
            "L": "1"
        }
    },
    "2": {
        "name": "fiat_25519_carry_mul_Pipeline_ARRAY_2_READ",
        "file": "d5.cpp",
        "fileloc": "0",
        "instructions": "70",
        "total_instructions": "70",
        "calls": "",
        "basicblocks": "15",
        "loads": {
            "L": "11"
        },
        "stores": {
            "L": "12"
        },
        "loops": {
            "L": "1"
        }
    },
    "0": {
        "name": "fiat_25519_carry_mul",
        "file": "d5.cpp",
        "fileloc": "3",
        "instructions": "446",
        "total_instructions": "626",
        "calls": "1 2 3",
        "basicblocks": "1",
        "loads": {
            "L": "20"
        }
    },
    "3": {
        "name": "fiat_25519_carry_mul_Pipeline_ARRAY_WRITE",
        "file": "d5.cpp",
        "fileloc": "0",
        "instructions": "40",
        "total_instructions": "40",
        "calls": "",
        "basicblocks": "4",
        "loads": {
            "L": "1"
        },
        "stores": {
            "L": "2"
        },
        "loops": {
            "L": "1"
        }
    }
}
